Workbook

Sheet 1. Inputs
A1: Adobe Inc. (ADBE) — MODEL INPUTS
A2: Every hard-coded number in this workbook lives on this sheet. Sheets 2 and 3 contain formulas only.
A3: AMBER = judgment / assumption input (change me). BLUE = reported actual from a primary source (fixed). White = formula.
B4: AMBER | C4: BLUE
A6: CONTENTS: A. Valuation, tax and policy scalars | B. Scenario probabilities and terminal multiples | C. Equity bridge (Q2 FY2026 balance sheet) | D. Off-balance-sheet hosting obligations | E. Shared forecast assumptions | F. Scenario drivers | G. Interim actuals for the TTM build
A8: A. VALUATION, TAX AND POLICY SCALARS
A9: Discount rate (r) | B9: 0.15 | K9: valuation.md §2 / §5.2: 'The discount rate is a stated variable, not a fitted one' — set at 15% per the brief, not derived from CAPM/WACC. valuation_calcs.py DISCOUNT_RATE.
A10: Normalised tax rate | B10: 0.21 | K10: owners_earnings_and_roic.md §2.3: '21% ... approximately the U.S. federal statutory rate, sits within a point of the FY2023-FY2026E average GAAP ETR of 20.1% ... between the two converging measures.' GAAP ETR 18-23%, cash rate 25-27%. JUDGMENT. Sensitivity there: 18% -> TTM OE $7,775M; 25% -> $7,111M.
A11: Discount rate for PV of purchase obligations | B11: 0.05 | K11: owners_earnings_calcs.py DISC (§5). JUDGMENT: roughly Adobe's marginal borrowing cost.
A12: Operating cash need, % of revenue | B12: 0.02 | K12: owners_earnings_and_roic.md §4: 'Adobe collects in advance and runs negative working capital, so its genuine operating cash requirement is small ... This is an assumption, not a sourced figure.' owners_earnings_calcs.py OPERATING_CASH_PCT.
A13: Terminal ROIC on incremental capital (Gordon cross-check only) | B13: 0.7 | K13: terminal_value.md §6.1 uses ROIC ~70% in the reinvestment drag term (1 - g/ROIC). owners_earnings_and_roic.md §1 reports TTM ROIC 72.0% (base) with a 43-45% conservative floor. Feeds the sheet-3 Gordon grid only — it does not affect the headline valuation.
A15: B. SCENARIO PROBABILITIES AND TERMINAL MULTIPLES
B16: Probability | C16: Terminal x | K16: Probabilities: forecast_earnings.md §1 — 'my judgment and are not sourced'. Terminal multiples: terminal_value.md §6.2 — ANALYST JUDGMENT, cross-checked against the Gordon grid and peer multiples on sheet 3.
A17: SEVERE | B17: 0.15 | C17: 7 | K17: terminal_value.md §6.2: terminal decline, AI substitutes the workflow. Gordon at g=-3%, r=10% -> 8.0x. Market precedent ZM 9.0x; SSTK 0.23x sales after a -70% year.
A18: BEAR | B18: 0.25 | C18: 11 | K18: terminal_value.md §6.2: grinding share loss, ~0-1% perpetual growth. Gordon at g=0-1%, r=9-10% -> 10.0x-12.3x. Floor cohort DBX 19.7x, GEN 18.0x, ZM 9.0x.
A19: BASE | B19: 0.4 | C19: 15 | K19: terminal_value.md §6.2: ~3% perpetual growth, 'the world where the question is neither resolved nor realised, so 15x — near today's actual and between the two peer cohorts — is the internally consistent choice.' Gordon at g=3%, r=9% -> 16.0x.
A20: BULL | B20: 0.2 | C20: 22 | K20: terminal_value.md §6.2: franchise durable, AI net accretive. Gordon at g=4%, r=8.5% ~ 21x. Mature-software median 27.2x; ADSK 33.8x. Set BELOW both.
A21: check: probabilities sum to 100% | B21: =SUM(B17:B20)
A23: C. EQUITY BRIDGE — Q2 FY2026 BALANCE SHEET (period ended 29 May 2026)
A24: Cash and cash equivalents | B24: 4919 | K24: primary_sources/2Q2026/financial_statements.md, consolidated balance sheet.
A25: Short-term investments | B25: 707 | K25: primary_sources/2Q2026/financial_statements.md, consolidated balance sheet.
A26: Debt, current (incl. $494M commercial paper), carrying value | B26: 1843 | K26: primary_sources/2Q2026/financial_statements.md, consolidated balance sheet. Commercial paper drawn $494M — 10-Q Note 14.
A27: Debt, long-term (senior notes), carrying value | B27: 4802 | K27: primary_sources/2Q2026/financial_statements.md, consolidated balance sheet.
A28: Operating lease liabilities, current | B28: 91 | K28: primary_sources/2Q2026/financial_statements.md, consolidated balance sheet.
A29: Operating lease liabilities, long-term | B29: 329 | K29: primary_sources/2Q2026/financial_statements.md, consolidated balance sheet.
A30: Shares outstanding, spot at 29 May 2026 (M) | B30: 399 | K30: primary_sources/2Q2026/financial_statements.md, consolidated balance sheet. A point-in-time count.
A31: Current dilutive effect of stock plans (M) | B31: 0.1 | K31: 10-Q Note 12: three-months-ended diluted w.a. 402.5M less basic w.a. 402.4M. Small because 12.1M potential shares are currently anti-dilutive.
A32: = Current diluted share count (M) | B32: =B30+B31 | K32: valuation.md §3 = 399.1M. Per the brief this is TODAY's share count: no forecast buyback shrinkage (notably NOT the FY2030E 341M in forecast_earnings.md §8). The 402.5M three-month weighted average was rejected as backward-looking and stale while Adobe repurchases continuously.
A34: D. OFF-BALANCE-SHEET HOSTING / DATA-CENTRE PURCHASE OBLIGATIONS
A35: $6,821M of non-cancellable unconditional purchase obligations 'primarily relating to contracts with vendors for third-party hosting and data center services' (owners_earnings_and_roic.md §4.1).
A36: FY2026 contractual obligation | B36: 2083 | K36: primary_sources/FY2025/financial_statements.md Note 16 maturity schedule; owners_earnings_calcs.py §5.
A37: FY2027 contractual obligation | B37: 1901
A38: FY2028 contractual obligation | B38: 1623
A39: FY2029 contractual obligation | B39: 1196
A40: FY2030 contractual obligation | B40: 12
A41: FY2031 contractual obligation | B41: 6
A42: Undiscounted total | B42: =SUM(B36:B41)
A43: = Present value, mid-year convention | B43: =SUMPRODUCT(B36:B41/(1+$B$11)^(ROW(B36:B41)-ROW($B$36)+0.5)) | K43: owners_earnings_and_roic.md §4.1 reports $6,259M at 5%. pv = SUM( v / 1.05^(i+0.5) ), i = 0..5 — owners_earnings_calcs.py §5.
A45: E. SHARED FORECAST ASSUMPTIONS (identical in all four scenarios)
F46: FY2026E | G46: FY2027E | H46: FY2028E | I46: FY2029E | J46: FY2030E | K46: forecast_earnings.md §8 — the lines that do not vary by scenario.
A47: Publishing & Advertising subscription growth | F47: -0.05 | G47: -0.05 | H47: -0.05 | I47: -0.05 | J47: -0.05 | K47: forecast_earnings_calcs.py §3 — run-off book. JUDGMENT.
A48: Product revenue growth | F48: -0.02 | G48: -0.05 | H48: -0.05 | I48: -0.05 | J48: -0.05 | K48: forecast_earnings_calcs.py §3 — perpetual-licence run-off. JUDGMENT.
A49: Services and other revenue growth | F49: -0.2 | G49: -0.12 | H49: -0.1 | I49: -0.08 | J49: -0.08 | K49: forecast_earnings_calcs.py §3 — 1H FY2026 annualised, then decline. JUDGMENT.
A50: Creative FX translation contribution | F50: 0.02 | G50: 0 | H50: 0 | I50: 0 | J50: 0 | K50: Q2 FY2026 FX added ~$94M net (causal_model.md Factor 1.7). Zero after FY2026: the model takes no currency view. forecast_earnings.md §4.
A51: Semrush revenue, $M (BEAR / BASE / BULL) | F51: 280 | G51: 500 | H51: 540 | I51: 578 | J51: 612 | K51: ~$280M guided FY2026 contribution (primary_sources/2Q2026/md_and_a.md), then annualises at 6-8%. Acquisition closed April 2026. JUDGMENT.
A52: Semrush revenue, $M — SEVERE case override | F52: 280 | G52: 470 | H52: 470 | I52: 470 | J52: 470 | K52: forecast_earnings_calcs.py §9 severe override sem=... . JUDGMENT.
A53: Purchased-intangible amortisation, disclosed schedule ($M) | F53: 222 | G53: 208 | H53: 151 | I53: 146 | J53: 143 | K53: primary_sources/2Q2026/financial_statements.md Note 7. FY2026 = $91M actual 1H + $131M scheduled remainder. Excludes future acquisitions, so it is a FLOOR on future amortisation.
A54: Non-recurring operating charges forecast ($M) | F54: 0 | G54: 0 | H54: 0 | I54: 0 | J54: 0 | K54: ASSUMPTION: no future one-off charges are forecast in any scenario. Adobe booked $1,078M in FY2024 (Figma termination fee plus lease impairments) and $162M in 1H FY2026 (goodwill impairment plus the FTC loss contingency), so zero is an optimistic convention, not a neutral one. Setting these cells non-zero reduces owners' earnings pound for pound. forecast_earnings.md forecasts no one-offs.
A56: Product cost ratio (cost of product / product revenue) | B56: 0.070769231 | K56: FY2025 actual $23M / $325M held flat. forecast_earnings_calcs.py PROD_COST_RATIO.
A57: Services cost ratio (cost of services / services revenue) | B57: 1.05 | K57: Services is loss-making: FY2025 0.928, 1H FY2026 1.085. JUDGMENT 1.05.
A58: FY2025 purchased-intangible amortisation inside cost of subscription ($M) | B58: 151 | K58: primary_sources/FY2025/financial_statements.md Note 8. Stripped out of the cost ratio because owners' earnings adds all purchased-intangible amortisation back.
A59: PP&E depreciation growth per year | B59: 0.05 | K59: forecast_earnings_calcs.py §8 chain(236.0, 5%). JUDGMENT.
A60: Maintenance capex, FY2025 base ($M) | B60: 241 | K60: = 3-year average actual capex FY2023-FY2025 ($240.667M), rounded — owners_earnings_and_roic.md §2.2: 'I use the three-year average actual capex of $241M as maintenance capex for every period — which lands within $5M of FY2025 depreciation.'
A61: Maintenance capex growth per year | B61: 0.05 | K61: forecast_earnings_calcs.py §8 chain(241.0, 5%). JUDGMENT. Depreciation and maintenance capex both grow 5%, so they effectively cancel.
A63: F. SCENARIO DRIVERS — the root-cause variables the forecast is built on
A64: Each scenario re-runs the identical engine on its own driver set (sheet 2 §5 and §6). forecast_earnings.md §2-§7; forecast_earnings_calcs.py §9 scenario().
A65: SEVERE — Generative AI SUBSTITUTES Adobe's creative workflows (as it did Adobe Stock); Adobe defends with price cuts and more advertising.
F66: FY2026E | G66: FY2027E | H66: FY2028E | I66: FY2029E | J66: FY2030E
A67: MAU growth (Acrobat/Express monthly active users) | F67: 0.17 | G67: 0.08 | H67: 0.04 | I67: 0.02 | J67: 0 | K67: Q4 FY2025 call: MAU 'surpassed 750 million ... growing 20% year-over-year'. Decay paths are JUDGMENT. forecast_earnings.md §3, causal_model.md Factor 1.1.
A68: Change in revenue per average MAU | F68: -0.055 | G68: -0.07 | H68: -0.06 | I68: -0.05 | J68: -0.045 | K68: The observable composite of free-to-paid conversion x price per paid seat; Adobe discloses neither component. forecast_earnings.md §3 flags confidence as LOW. JUDGMENT.
A69: Creative paid-unit (volume) growth | F69: 0.06 | G69: 0 | H69: -0.04 | I69: -0.05 | J69: -0.05 | K69: forecast_earnings.md §4: base decays 7.8% -> 3.0%; 'the bear case takes volume to 0% by FY2030 and the severe case to -5%'. JUDGMENT.
A70: Creative value-based price / tier-mix growth | F70: 0 | G70: 0 | H70: 0 | I70: 0 | J70: 0 | K70: forecast_earnings.md §4 — value-based pricing and tier mix. JUDGMENT.
A71: Digital Experience subscription growth | F71: 0.08 | G71: 0.04 | H71: 0.025 | I71: 0.02 | J71: 0.015 | K71: forecast_earnings.md §5 — enterprise seat expansion and cross-sell. JUDGMENT.
A72: Subscription cost ratio drift, ex-amortisation (bp/yr) | F72: 90 | G72: 100 | H72: 90 | I72: 80 | J72: 70 | K72: THE key cost finding: on an ex-amortisation basis the hosting/AI-inference cost ratio is deteriorating ~60bp/yr right now. forecast_earnings.md §6. JUDGMENT on the decay path.
A73: Advertising, % of revenue | F73: 0.076 | G73: 0.076 | H73: 0.076 | I73: 0.076 | J73: 0.076 | K73: The freemium funnel spend, up 31.7% in FY2025 to $1,370M. forecast_earnings.md §7. JUDGMENT.
A74: Other sales & marketing, % of revenue | F74: 0.218 | G74: 0.218 | H74: 0.218 | I74: 0.218 | J74: 0.218 | K74: forecast_earnings.md §7 — sales-force operating leverage. JUDGMENT.
A75: Research & development, % of revenue | F75: 0.195 | G75: 0.195 | H75: 0.195 | I75: 0.195 | J75: 0.195 | K75: forecast_earnings.md §7: base 18.0%, 'bear case uses 18.7% and the severe case 19.5%'. JUDGMENT.
A76: General & administrative, % of revenue | F76: 0.069 | G76: 0.069 | H76: 0.069 | I76: 0.069 | J76: 0.069 | K76: forecast_earnings.md §7 — held flat at the FY2025 ratio in all scenarios except SEVERE (6.9%). JUDGMENT.
A78: BEAR — AI substitution bites Creative, freemium advertising never comes down, inference cost keeps compounding, BP&C monetisation keeps eroding.
F79: FY2026E | G79: FY2027E | H79: FY2028E | I79: FY2029E | J79: FY2030E
A80: MAU growth (Acrobat/Express monthly active users) | F80: 0.18 | G80: 0.11 | H80: 0.08 | I80: 0.06 | J80: 0.04
A81: Change in revenue per average MAU | F81: -0.045 | G81: -0.045 | H81: -0.035 | I81: -0.03 | J81: -0.03
A82: Creative paid-unit (volume) growth | F82: 0.07 | G82: 0.035 | H82: 0.02 | I82: 0.01 | J82: 0
A83: Creative value-based price / tier-mix growth | F83: 0.005 | G83: 0.01 | H83: 0.01 | I83: 0.01 | J83: 0.01
A84: Digital Experience subscription growth | F84: 0.085 | G84: 0.06 | H84: 0.05 | I84: 0.045 | J84: 0.04
A85: Subscription cost ratio drift, ex-amortisation (bp/yr) | F85: 80 | G85: 75 | H85: 65 | I85: 60 | J85: 55
A86: Advertising, % of revenue | F86: 0.07 | G86: 0.073 | H86: 0.073 | I86: 0.073 | J86: 0.073
A87: Other sales & marketing, % of revenue | F87: 0.213 | G87: 0.213 | H87: 0.213 | I87: 0.213 | J87: 0.213
A88: Research & development, % of revenue | F88: 0.187 | G88: 0.187 | H88: 0.187 | I88: 0.187 | J88: 0.187
A89: General & administrative, % of revenue | F89: 0.067 | G89: 0.067 | H89: 0.067 | I89: 0.067 | J89: 0.067
A91: BASE — Freemium reach compounds but monetises at a falling rate; hosting/AI cost drift decays; modest operating leverage in S&M.
F92: FY2026E | G92: FY2027E | H92: FY2028E | I92: FY2029E | J92: FY2030E
A93: MAU growth (Acrobat/Express monthly active users) | F93: 0.18 | G93: 0.13 | H93: 0.1 | I93: 0.08 | J93: 0.06
A94: Change in revenue per average MAU | F94: -0.035 | G94: -0.025 | H94: -0.01 | I94: 0 | J94: 0
A95: Creative paid-unit (volume) growth | F95: 0.078 | G95: 0.06 | H95: 0.05 | I95: 0.04 | J95: 0.03
A96: Creative value-based price / tier-mix growth | F96: 0.005 | G96: 0.02 | H96: 0.02 | I96: 0.02 | J96: 0.02
A97: Digital Experience subscription growth | F97: 0.09 | G97: 0.08 | H97: 0.075 | I97: 0.07 | J97: 0.065
A98: Subscription cost ratio drift, ex-amortisation (bp/yr) | F98: 72 | G98: 50 | H98: 35 | I98: 25 | J98: 20
A99: Advertising, % of revenue | F99: 0.069 | G99: 0.0695 | H99: 0.065 | I99: 0.061 | J99: 0.058
A100: Other sales & marketing, % of revenue | F100: 0.21 | G100: 0.207 | H100: 0.204 | I100: 0.2015 | J100: 0.1995
A101: Research & development, % of revenue | F101: 0.18 | G101: 0.18 | H101: 0.18 | I101: 0.18 | J101: 0.18
A102: General & administrative, % of revenue | F102: 0.067 | G102: 0.067 | H102: 0.067 | I102: 0.067 | J102: 0.067
A104: BULL — Freemium converts, unit inference-cost deflation outruns volume growth, advertising normalises after FY2027, price optimisations resume in full.
F105: FY2026E | G105: FY2027E | H105: FY2028E | I105: FY2029E | J105: FY2030E
A106: MAU growth (Acrobat/Express monthly active users) | F106: 0.19 | G106: 0.15 | H106: 0.12 | I106: 0.1 | J106: 0.08
A107: Change in revenue per average MAU | F107: -0.03 | G107: -0.005 | H107: 0.01 | I107: 0.015 | J107: 0.015
A108: Creative paid-unit (volume) growth | F108: 0.085 | G108: 0.085 | H108: 0.075 | I108: 0.065 | J108: 0.055
A109: Creative value-based price / tier-mix growth | F109: 0.005 | G109: 0.03 | H109: 0.03 | I109: 0.03 | J109: 0.03
A110: Digital Experience subscription growth | F110: 0.095 | G110: 0.095 | H110: 0.09 | I110: 0.085 | J110: 0.08
A111: Subscription cost ratio drift, ex-amortisation (bp/yr) | F111: 60 | G111: 25 | H111: 10 | I111: 0 | J111: -10
...

Sheet 2. Owners Earnings
A1: Adobe Inc. (ADBE) — OWNERS' EARNINGS: HISTORICAL AND PROJECTED ($M)
A2: Historical actuals (columns B-E) and the BASE-case forecast (columns F-J) are built on ONE identical construction, so the columns are directly comparable left to right. The other three scenarios run the same engine in §6 and are summarised in §7.
A3: AMBER = judgment input (all on sheet 1) BLUE = reported actual from a primary source GREEN = headline output white = formula
A4: CONTENTS: §1 The owners' earnings bridge (the answer) | §2 Supporting detail for the historical adjustments | §3 Reported income statement and the TTM build | §4 Customer-group revenue, the forecast's starting base | §5 Forecast build, BASE case | §6 The other three scenario engines | §7 Owners' earnings by scenario | §8 Checks
A6: ($M unless noted) | B6: FY2023A | C6: FY2024A | D6: FY2025A | E6: TTM Q2FY26 | F6: FY2026E | G6: FY2027E | H6: FY2028E | I6: FY2029E | J6: FY2030E | K6: CAGR FY23-25 | L6: CAGR FY25-30E | M6: Source / note
A8: §1. THE OWNERS' EARNINGS BRIDGE — HISTORICAL ACTUAL AND PROJECTED, SIDE BY SIDE
A9: EBIT + non-recurring charges + purchased-intangible amortisation = EBITA; + PP&E depreciation − maintenance capex = pre-tax owners' earnings; x (1 − normalised tax rate) = OWNERS' EARNINGS. Stock-based compensation is deliberately NOT added back — it is a real cost to owners and stays inside EBIT (owners_earnings_and_roic.md §2.1).
A11: TOTAL REVENUE (memo) | B11: =B53 | C11: =C53 | D11: =D53 | E11: =E53 | F11: =F92 | G11: =G92 | H11: =H92 | I11: =I92 | J11: =J92 | K11: =IFERROR((D11/B11)^(1/2)-1,"") | L11: =IFERROR((J11/D11)^(1/5)-1,"") | M11: Historical from §3; forecast from §5. Shown here only to compute margins.
A13: Operating income (EBIT) | B13: =B63 | C13: =C63 | D13: =D63 | E13: =E63 | F13: =F105-'1. Inputs'!F$53 | G13: =G105-'1. Inputs'!G$53 | H13: =H105-'1. Inputs'!H$53 | I13: =I105-'1. Inputs'!I$53 | J13: =J105-'1. Inputs'!J$53 | M13: Historical: as reported (§3). Forecast: DERIVED as driver-built EBITA (§5) less Adobe's own disclosed forward amortisation schedule (sheet 1 §E), which excludes future acquisitions and is therefore a floor on amortisation.
A14: + non-recurring charges booked in operating expenses | B14: =B40 | C14: =C40 | D14: =D40 | E14: =E40 | F14: ='1. Inputs'!F$54 | G14: ='1. Inputs'!G$54 | H14: ='1. Inputs'!H$54 | I14: ='1. Inputs'!I$54 | J14: ='1. Inputs'!J$54 | M14: Detail in §2. FY2024 $1,078M = $1,000M Figma termination fee + $78M lease impairments; TTM $162M = $70M goodwill impairment + $92M FTC loss contingency, both booked in 1H FY2026 so neither is rolled (owners_earnings_calcs.py §3).
A15: + amortisation of purchased intangibles | B15: 375 | C15: 336 | D15: 310 | E15: =D15-'1. Inputs'!$B$131+'1. Inputs'!$C$131 | F15: ='1. Inputs'!F$53 | G15: ='1. Inputs'!G$53 | H15: ='1. Inputs'!H$53 | I15: ='1. Inputs'!I$53 | J15: ='1. Inputs'!J$53 | M15: FY2025 10-K Note 8 / Q2 FY2026 10-Q Note 7. Added back because the acquired asset base is maintained by R&D and S&M that are already expensed inside EBIT, while the capital itself stays in invested capital.
A16: = EBITA | B16: =B13+B14+B15 | C16: =C13+C14+C15 | D16: =D13+D14+D15 | E16: =E13+E14+E15 | F16: =F13+F14+F15 | G16: =G13+G14+G15 | H16: =H13+H14+H15 | I16: =I13+I14+I15 | J16: =J13+J14+J15 | K16: =IFERROR((D16/B16)^(1/2)-1,"") | L16: =IFERROR((J16/D16)^(1/5)-1,"") | M16: Earnings before interest, tax and purchased-intangible amortisation — the basis owners' earnings is built on.
A17: EBITA margin | B17: =B16/B11 | C17: =C16/C11 | D17: =D16/D11 | E17: =E16/E11 | F17: =F16/F11 | G17: =G16/G11 | H17: =H16/H11 | I17: =I16/I11 | J17: =J16/J11
A18: + PP&E depreciation | B18: 235 | C18: 239 | D18: 236 | E18: 236 | F18: =$D18*(1+'1. Inputs'!$B$59)^1 | G18: =$D18*(1+'1. Inputs'!$B$59)^2 | H18: =$D18*(1+'1. Inputs'!$B$59)^3 | I18: =$D18*(1+'1. Inputs'!$B$59)^4 | J18: =$D18*(1+'1. Inputs'!$B$59)^5 | M18: FY2025 10-K Note 6. TTM is NOT rolled: depreciation is not separately disclosed in the 10-Q and net PP&E is essentially unchanged ($1,873M -> $1,870M), so FY2025's $236M is carried (owners_earnings_calcs.py §3).
A19: − maintenance capex | B19: =-AVERAGE($B42:$D42) | C19: =-AVERAGE($B42:$D42) | D19: =-AVERAGE($B42:$D42) | E19: =-AVERAGE($B42:$D42) | F19: =-'1. Inputs'!$B$60*(1+'1. Inputs'!$B$61)^1 | G19: =-'1. Inputs'!$B$60*(1+'1. Inputs'!$B$61)^2 | H19: =-'1. Inputs'!$B$60*(1+'1. Inputs'!$B$61)^3 | I19: =-'1. Inputs'!$B$60*(1+'1. Inputs'!$B$61)^4 | J19: =-'1. Inputs'!$B$60*(1+'1. Inputs'!$B$61)^5 | M19: 3-year average of ACTUAL capex FY2023-FY2025 (§2) = $240.7M, applied to every historical period; grown 5%/yr in the forecast off the rounded $241M base on sheet 1. owners_earnings_and_roic.md §2.2 — 'Using one year's depressed capex would flatter owners' earnings.'
A20: = pre-tax owners' earnings | B20: =B16+B18+B19 | C20: =C16+C18+C19 | D20: =D16+D18+D19 | E20: =E16+E18+E19 | F20: =F16+F18+F19 | G20: =G16+G18+G19 | H20: =H16+H18+H19 | I20: =I16+I18+I19 | J20: =J16+J18+J19
A21: − normalised tax | B21: =-B20*'1. Inputs'!$B$10 | C21: =-C20*'1. Inputs'!$B$10 | D21: =-D20*'1. Inputs'!$B$10 | E21: =-E20*'1. Inputs'!$B$10 | F21: =-F20*'1. Inputs'!$B$10 | G21: =-G20*'1. Inputs'!$B$10 | H21: =-H20*'1. Inputs'!$B$10 | I21: =-I20*'1. Inputs'!$B$10 | J21: =-J20*'1. Inputs'!$B$10 | M21: At the single normalised rate on sheet 1 §A (21%), applied identically to every period and every scenario.
A22: = OWNERS' EARNINGS | B22: =B20+B21 | C22: =C20+C21 | D22: =D20+D21 | E22: =E20+E21 | F22: =F20+F21 | G22: =G20+G21 | H22: =H20+H21 | I22: =I20+I21 | J22: =J20+J21 | K22: =IFERROR((D22/B22)^(1/2)-1,"") | L22: =IFERROR((J22/D22)^(1/5)-1,"") | M22: Method A, owners_earnings_and_roic.md §1-§2. Forecast columns are the BASE case; §7 shows all four scenarios.
A23: owners' earnings margin (% of revenue) | B23: =B22/B11 | C23: =C22/C11 | D23: =D22/D11 | E23: =E22/E11 | F23: =F22/F11 | G23: =G22/G11 | H23: =H22/H11 | I23: =I22/I11 | J23: =J22/J11
A24: owners' earnings growth, year on year | C24: =C22/B22-1 | D24: =D22/C22-1 | F24: =F22/D22-1 | G24: =G22/F22-1 | H24: =H22/G22-1 | I24: =I22/H22-1 | J24: =J22/I22-1 | M24: No growth is shown for the TTM column: it overlaps FY2025 and is not a clean year-on-year comparison. FY2026E growth is struck off FY2025A.
A26: NO forecast share count, buyback path or forecast owners' earnings per share is modelled anywhere in this workbook. Projecting them requires stacking three further judgment assumptions — a buyback payout ratio, a stock-based compensation ratio, and an assumed repurchase PRICE — and the price assumption is circular with the valuation the model is trying to produce. The valuation on sheet 3 uses TODAY's diluted share count of 399.1M throughout, per the brief (valuation.md §3), so none of it would change the answer. Adobe's actual buyback pace is shown below as history only.
A27: memo: stock-based compensation (deducted inside EBIT, never added back) | B27: 1718 | C27: 1833 | D27: 1942 | E27: =D27-'1. Inputs'!$B$134+'1. Inputs'!$C$134 | M27: FY2025 10-K Note 12. Cross-checked against shares actually delivered: 4.8M shares at a ~$408 weighted-average grant-date fair value ~ $1,920M against the $1,942M GAAP charge, within ~1% (owners_earnings_and_roic.md §2.1).
A28: memo: diluted shares (M) — HISTORICAL ONLY | B28: 459.1 | C28: 449.7 | D28: 427 | E28: =D28-'1. Inputs'!$B$135+'1. Inputs'!$C$135 | M28: owners_earnings_calcs.py §7. TTM uses the same TTM convention: 427.0 − 433.2 + 406.6 = 400.4M. NO forecast share count is modelled — see the note below.
A29: memo: OWNERS' EARNINGS PER DILUTED SHARE — HISTORICAL ONLY | B29: =B22/B28 | C29: =C22/C28 | D29: =D22/D28 | E29: =E22/E28 | K29: =IFERROR((D29/B29)^(1/2)-1,"") | M29: owners_earnings_and_roic.md §1: $12.08 / $14.32 / $16.67 / $18.71. Reported actuals divided by reported share counts — no assumption in them.
A30: memo: buyback spend, ACTUAL — HISTORICAL ONLY | B30: 4400 | C30: 9500 | D30: 11281 | M30: owners_earnings_and_roic.md §5; 1H FY2026 spend was $4,589M. Shown as history, not extrapolated.
A31: actual buyback as a multiple of owners' earnings | B31: =B30/B22 | C31: =C30/C22 | D31: =D30/D22 | M31: Adobe repurchased at ~1.5-1.6x owners' earnings in FY2024-FY2025 — it spent more than it earned. terminal_value.md §9 flags that if that pace continues 'the equity bridge stops being immaterial'. That is a stated RISK to the sheet-3 bridge, not a modelled forecast.
A33: §2. SUPPORTING DETAIL FOR THE HISTORICAL OWNERS' EARNINGS ADJUSTMENTS
A34: Every add-back used in §1, itemised and sourced. This is the audit trail for the historical bridge.
A36: Figma acquisition termination fee | B36: 0 | C36: =C62 | D36: 0 | E36: 0 | M36: FY2024 one-off, $1,000M, disclosed on its own income-statement line (primary_sources/FY2025/md_and_a.md). Pulled from §3 so it cannot drift.
A37: Lease-related asset impairments | B37: 0 | C37: 78 | D37: 0 | E37: 0 | M37: FY2024, $78M — FY2025 10-K cash-flow statement; Note 7 places the charge in G&A. owners_earnings_and_roic.md §2.1.
A38: Goodwill impairment, Publishing & Advertising | B38: 0 | C38: 0 | D38: 0 | E38: ='1. Inputs'!$C$132 | M38: $70M, Q2 FY2026 10-Q Note 7. Booked in 1H FY2026, so it enters the TTM column directly and is NOT rolled through the FY25 − 1H25 + 1H26 formula.
A39: FTC/DOJ ROSCA loss contingency accrual | B39: 0 | C39: 0 | D39: 0 | E39: ='1. Inputs'!$C$133 | M39: $92M, 1H FY2026. Same treatment as the goodwill impairment above.
A40: = total non-recurring charges added back in §1 | B40: =SUM(B36:B39) | C40: =SUM(C36:C39) | D40: =SUM(D36:D39) | E40: =SUM(E36:E39) | M40: FY2023 $0M, FY2024 $1,078M, FY2025 $0M ('none in FY2025'), TTM $162M — owners_earnings_and_roic.md §2.1.
A42: memo: capital expenditure, ACTUAL | B42: 360 | C42: 183 | D42: 179 | E42: 201 | M42: FY2025 10-K and Q2 FY2026 10-Q cash-flow statements. Net PP&E has been SHRINKING ($1,936M -> $1,873M -> $1,870M), i.e. recent capex runs below depreciation — which is why a 3-year average, not the latest year, is used as maintenance capex.
A43: 3-year average actual capex FY2023-FY2025 ( = maintenance capex applied to every historical period) | B43: =AVERAGE(B42:D42) | M43: $240.667M. owners_earnings_and_roic.md §2.2 notes this 'lands within $5M of FY2025 depreciation, a useful independent confirmation that it is the right order of magnitude'. Sensitivity there: +/-$60M of capex moves owners' earnings by ~$47M after tax, ~0.6%.
A45: NOT adjusted, deliberately: (a) stock-based compensation is a real cost to owners and stays inside EBIT; (b) the $6,821M of hosting purchase obligations are contracted OPERATING spend already flowing through cost of revenue as incurred, so adding a charge would double-count — they are instead treated as a debt-like item in the equity bridge on sheet 3; (c) the deferred-revenue float is not counted as earnings. owners_earnings_and_roic.md §2.1, §4.1.
A47: §3. REPORTED INCOME STATEMENT — THE SOURCE OF THE EBIT LINE IN §1
A48: FY2023A-FY2025A as reported. The TTM Q2 FY2026 column is built as FY2025 − 1H FY2025 + 1H FY2026 from the interim actuals on sheet 1 §G.
A50: Subscription revenue | B50: 18284 | C50: 20521 | D50: 22904 | E50: =D50-'1. Inputs'!$B$120+'1. Inputs'!$C$120 | M50: primary_sources/FY2025/financial_statements.md, Consolidated Statements of Income.
A51: Product revenue | B51: 460 | C51: 386 | D51: 325 | E51: =D51-'1. Inputs'!$B$121+'1. Inputs'!$C$121
A52: Services and other revenue | B52: 665 | C52: 598 | D52: 540 | E52: =D52-'1. Inputs'!$B$122+'1. Inputs'!$C$122
A53: TOTAL REVENUE | B53: =B50+B51+B52 | C53: =C50+C51+C52 | D53: =D50+D51+D52 | E53: =E50+E51+E52
A54: Cost of subscription revenue | B54: 1822 | C54: 1799 | D54: 2027 | E54: =D54-'1. Inputs'!$B$123+'1. Inputs'!$C$123
A55: Cost of product revenue | B55: 29 | C55: 25 | D55: 23 | E55: =D55-'1. Inputs'!$B$124+'1. Inputs'!$C$124
A56: Cost of services and other revenue | B56: 503 | C56: 534 | D56: 501 | E56: =D56-'1. Inputs'!$B$125+'1. Inputs'!$C$125
A57: Gross profit | B57: =B53-B54-B55-B56 | C57: =C53-C54-C55-C56 | D57: =D53-D54-D55-D56 | E57: =E53-E54-E55-E56
A58: Research and development | B58: 3473 | C58: 3944 | D58: 4294 | E58: =D58-'1. Inputs'!$B$126+'1. Inputs'!$C$126
A59: Sales and marketing | B59: 5351 | C59: 5764 | D59: 6488 | E59: =D59-'1. Inputs'!$B$127+'1. Inputs'!$C$127
A60: General and administrative | B60: 1413 | C60: 1529 | D60: 1573 | E60: =D60-'1. Inputs'!$B$128+'1. Inputs'!$C$128
A61: Amortisation of intangibles (operating expense line) | B61: 168 | C61: 169 | D61: 157 | E61: =D61-'1. Inputs'!$B$129+'1. Inputs'!$C$129
A62: Figma acquisition termination fee | B62: 0 | C62: 1000 | D62: 0 | E62: 0 | M62: FY2024 one-off, $1,000M — primary_sources/FY2025/md_and_a.md.
A63: OPERATING INCOME (EBIT) | B63: =B57-B58-B59-B60-B61-B62 | C63: =C57-C58-C59-C60-C61-C62 | D63: =D57-D58-D59-D60-D61-D62 | E63: =E57-E58-E59-E60-E61-E62
A64: check: EBIT as reported in the 10-K / 10-Q | B64: 6650 | C64: 6741 | D64: 8706 | E64: =D64-'1. Inputs'!$B$130+'1. Inputs'!$C$130 | M64: The row above is built up from the individual revenue and expense lines; this is the figure Adobe reports. The difference must be zero.
A65: difference (must be 0) | B65: =B63-B64 | C65: =C63-C64 | D65: =D63-D64 | E65: =E63-E64
A67: §4. CUSTOMER-GROUP SUBSCRIPTION REVENUE — THE FORECAST'S STARTING BASE
A69: Creative & Marketing Professionals subscription | B69: 13425 | C69: 14749 | D69: 16303 | M69: primary_sources/FY2025/md_and_a.md.
A70: Business Professionals & Consumers subscription (Acrobat/Express) | B70: 4744 | C70: 5662 | D70: 6495 | M70: primary_sources/FY2025/md_and_a.md.
A71: Publishing & Advertising subscription | B71: 115 | C71: 110 | D71: 106 | M71: primary_sources/FY2025/md_and_a.md.
A72: check: the three groups sum to total subscription revenue (difference must be 0) | B72: =B69+B70+B71-B50 | C72: =C69+C70+C71-C50 | D72: =D69+D70+D71-D50
A73: Digital Experience segment subscription revenue | B73: 4331 | C73: 4864 | D73: 5409 | M73: primary_sources/FY2025/md_and_a.md.
A74: Creative flagship subscription (DERIVED = C&MP − Digital Experience) | B74: =B69-B73 | C74: =C69-C73 | D74: =D69-D73 | M74: C&MP is defined as the Digital Experience offerings PLUS the Creative Cloud flagship, so the Creative line is only obtainable by subtraction (forecast_earnings_calcs.py §0). Adobe does not disclose it directly.
A76: §5. FORECAST BUILD — BASE CASE. Column D repeats the FY2025A anchor each driver is grown off, so the join between actual and forecast is visible.
A78: Revenue drivers
A79: Acrobat/Express MAU exiting fiscal year (M) | C79: =D79/1.2 | D79: 750 | F79: =D79*(1+'1. Inputs'!F$93) | G79: =F79*(1+'1. Inputs'!G$93) | H79: =G79*(1+'1. Inputs'!H$93) | I79: =H79*(1+'1. Inputs'!I$93) | J79: =I79*(1+'1. Inputs'!J$93) | M79: Q4 FY2025 call: MAU 'surpassed 750 million ... growing 20% year-over-year', so the FY2024 exit count is DERIVED as 750/1.20. causal_model.md Factor 1.1.
A80: MAU growth | D80: =D79/C79-1 | F80: ='1. Inputs'!F$93 | G80: ='1. Inputs'!G$93 | H80: ='1. Inputs'!H$93 | I80: ='1. Inputs'!I$93 | J80: ='1. Inputs'!J$93
A81: Average MAU (M) | D81: =(C79+D79)/2 | F81: =(D79+F79)/2 | G81: =(F79+G79)/2 | H81: =(G79+H79)/2 | I81: =(H79+I79)/2 | J81: =(I79+J79)/2 | M81: Revenue is earned across the year, so it is struck on the average of the opening and closing MAU count, not the exit count.
A82: Revenue per average MAU ($/yr) | D82: =D70/D81 | F82: =D82*(1+'1. Inputs'!F$94) | G82: =F82*(1+'1. Inputs'!G$94) | H82: =G82*(1+'1. Inputs'!H$94) | I82: =H82*(1+'1. Inputs'!I$94) | J82: =I82*(1+'1. Inputs'!J$94) | M82: The observable composite of free-to-paid conversion x price per paid seat. Adobe discloses NEITHER component, which is why forecast_earnings.md §3 flags this driver's confidence as LOW. It is the single largest swing factor in the BP&C line.
A84: BP&C subscription revenue (Acrobat/Express) | D84: =D70 | F84: =F81*F82 | G84: =G81*G82 | H84: =H81*H82 | I84: =I81*I82 | J84: =J81*J82
A85: Creative subscription revenue | D85: =D74 | F85: =D85*(1+'1. Inputs'!F$95+'1. Inputs'!F$96+'1. Inputs'!F$50) | G85: =F85*(1+'1. Inputs'!G$95+'1. Inputs'!G$96+'1. Inputs'!G$50) | H85: =G85*(1+'1. Inputs'!H$95+'1. Inputs'!H$96+'1. Inputs'!H$50) | I85: =H85*(1+'1. Inputs'!I$95+'1. Inputs'!I$96+'1. Inputs'!I$50) | J85: =I85*(1+'1. Inputs'!J$95+'1. Inputs'!J$96+'1. Inputs'!J$50) | M85: Grown by paid-unit volume + value-based price/tier mix + FX translation, the three drivers added rather than compounded (forecast_earnings.md §4).
A86: Digital Experience subscription revenue | D86: =D73 | F86: =D86*(1+'1. Inputs'!F$97) | G86: =F86*(1+'1. Inputs'!G$97) | H86: =G86*(1+'1. Inputs'!H$97) | I86: =H86*(1+'1. Inputs'!I$97) | J86: =I86*(1+'1. Inputs'!J$97)
A87: Semrush revenue (acquisition closed April 2026) | D87: 0 | F87: ='1. Inputs'!F$51 | G87: ='1. Inputs'!G$51 | H87: ='1. Inputs'!H$51 | I87: ='1. Inputs'!I$51 | J87: ='1. Inputs'!J$51 | M87: Zero in FY2025 because the acquisition had not closed. primary_sources/2Q2026/md_and_a.md guides ~$280M of FY2026 contribution.
A88: Publishing & Advertising subscription revenue | D88: =D71 | F88: =D88*(1+'1. Inputs'!F$47) | G88: =F88*(1+'1. Inputs'!G$47) | H88: =G88*(1+'1. Inputs'!H$47) | I88: =H88*(1+'1. Inputs'!I$47) | J88: =I88*(1+'1. Inputs'!J$47)
A89: Product revenue | D89: =D51 | F89: =D89*(1+'1. Inputs'!F$48) | G89: =F89*(1+'1. Inputs'!G$48) | H89: =G89*(1+'1. Inputs'!H$48) | I89: =H89*(1+'1. Inputs'!I$48) | J89: =I89*(1+'1. Inputs'!J$48)
A90: Services and other revenue | D90: =D52 | F90: =D90*(1+'1. Inputs'!F$49) | G90: =F90*(1+'1. Inputs'!G$49) | H90: =G90*(1+'1. Inputs'!H$49) | I90: =H90*(1+'1. Inputs'!I$49) | J90: =I90*(1+'1. Inputs'!J$49)
A91: Total subscription revenue | D91: =D50 | F91: =F84+F85+F86+F87+F88 | G91: =G84+G85+G86+G87+G88 | H91: =H84+H85+H86+H87+H88 | I91: =I84+I85+I86+I87+I88 | J91: =J84+J85+J86+J87+J88
A92: TOTAL REVENUE | D92: =D53 | F92: =F91+F89+F90 | G92: =G91+G89+G90 | H92: =H91+H89+H90 | I92: =I91+I89+I90 | J92: =J91+J89+J90
A93: total revenue growth | F93: =F92/D92-1 | G93: =G92/F92-1 | H93: =H92/G92-1 | I93: =I92/H92-1 | J93: =J92/I92-1
A95: Cost drivers and EBITA (EBITA = EBIT before purchased-intangible amortisation)
A96: Subscription cost ratio, ex purchased-intangible amortisation | D96: =(D54-'1. Inputs'!$B$58)/D91 | F96: =D96+'1. Inputs'!F$98/10000 | G96: =F96+'1. Inputs'!G$98/10000 | H96: =G96+'1. Inputs'!H$98/10000 | I96: =H96+'1. Inputs'!I$98/10000 | J96: =I96+'1. Inputs'!J$98/10000 | M96: THE key cost finding: on this ex-amortisation basis the hosting / AI-inference cost ratio is deteriorating ~60bp/yr right now (forecast_earnings.md §6). The base case assumes that drift DECAYS from 72bp to 20bp/yr; the bear and severe cases assume it does not.
A97: Cost of subscription revenue, ex-amortisation | D97: =D54-'1. Inputs'!$B$58 | F97: =F91*F96 | G97: =G91*G96 | H97: =H91*H96 | I97: =I91*I96 | J97: =J91*J96
A98: Cost of product revenue | D98: =D55 | F98: =F89*'1. Inputs'!$B$56 | G98: =G89*'1. Inputs'!$B$56 | H98: =H89*'1. Inputs'!$B$56 | I98: =I89*'1. Inputs'!$B$56 | J98: =J89*'1. Inputs'!$B$56
A99: Cost of services and other revenue | D99: =D56 | F99: =F90*'1. Inputs'!$B$57 | G99: =G90*'1. Inputs'!$B$57 | H99: =H90*'1. Inputs'!$B$57 | I99: =I90*'1. Inputs'!$B$57 | J99: =J90*'1. Inputs'!$B$57
A100: Gross profit, ex-amortisation | D100: =D92-D97-D98-D99 | F100: =F92-F97-F98-F99 | G100: =G92-G97-G98-G99 | H100: =H92-H97-H98-H99 | I100: =I92-I97-I98-I99 | J100: =J92-J97-J98-J99
A101: Advertising expense | B101: 970 | C101: 1040 | D101: 1370 | F101: =F92*'1. Inputs'!F$99 | G101: =G92*'1. Inputs'!G$99 | H101: =H92*'1. Inputs'!H$99 | I101: =I92*'1. Inputs'!I$99 | J101: =J92*'1. Inputs'!J$99 | M101: primary_sources/FY2025/financial_statements.md Note 1 — the freemium funnel spend, up 31.7% in FY2025. Split out of sales & marketing because it is the cost of the MAU growth driver above.
A102: Other sales & marketing expense | D102: =D59-D101 | F102: =F92*'1. Inputs'!F$100 | G102: =G92*'1. Inputs'!G$100 | H102: =H92*'1. Inputs'!H$100 | I102: =I92*'1. Inputs'!I$100 | J102: =J92*'1. Inputs'!J$100
A103: Research and development | D103: =D58 | F103: =F92*'1. Inputs'!F$101 | G103: =G92*'1. Inputs'!G$101 | H103: =H92*'1. Inputs'!H$101 | I103: =I92*'1. Inputs'!I$101 | J103: =J92*'1. Inputs'!J$101
A104: General and administrative | D104: =D60 | F104: =F92*'1. Inputs'!F$102 | G104: =G92*'1. Inputs'!G$102 | H104: =H92*'1. Inputs'!H$102 | I104: =I92*'1. Inputs'!I$102 | J104: =J92*'1. Inputs'!J$102
A105: EBITA (driver-built) | D105: =D100-D101-D102-D103-D104 | F105: =F100-F101-F102-F103-F104 | G105: =G100-G101-G102-G103-G104 | H105: =H100-H101-H102-H103-H104 | I105: =I100-I101-I102-I103-I104 | J105: =J100-J101-J102-J103-J104
A106: EBITA margin | D106: =D105/D92 | F106: =F105/F92 | G106: =G105/G92 | H106: =H105/H92 | I106: =I105/I92 | J106: =J105/J92
A107: check: driver-built EBITA less the §1 bridge EBITA, FY2025A | D107: =D105-D16 | M107: FY2025 gap = −$2M, disclosed rather than hidden. Reported total purchased-intangible amortisation is $310M, but only $151M sits in cost of subscription and $157M in the amortisation opex line ($308M); ~$2M is inside other operating expense lines. The bridge anchors on the $310M add-back while the cost ratio is struck on the $151M figure — a 0.02% inconsistency carried over unchanged from forecast_earnings_calcs.py.
A109: §6. THE OTHER THREE SCENARIO ENGINES — identical construction to §5, run on each scenario's own drivers (sheet 1 §F)
A110: Shared lines (Publishing & Advertising, product, services, depreciation, maintenance capex, tax) are pulled from the base build rather than re-derived, so a change there propagates to every scenario.
A112: SEVERE — Generative AI SUBSTITUTES Adobe's creative workflows (as it did Adobe Stock); Adobe defends with price cuts and more advertising.
A113: MAU exiting year (M) | F113: =$D79*(1+'1. Inputs'!F$67) | G113: =F113*(1+'1. Inputs'!G$67) | H113: =G113*(1+'1. Inputs'!H$67) | I113: =H113*(1+'1. Inputs'!I$67) | J113: =I113*(1+'1. Inputs'!J$67)
A114: Average MAU (M) | F114: =($D79+F113)/2 | G114: =(F113+G113)/2 | H114: =(G113+H113)/2 | I114: =(H113+I113)/2 | J114: =(I113+J113)/2
A115: Revenue per average MAU ($/yr) | F115: =$D82*(1+'1. Inputs'!F$68) | G115: =F115*(1+'1. Inputs'!G$68) | H115: =G115*(1+'1. Inputs'!H$68) | I115: =H115*(1+'1. Inputs'!I$68) | J115: =I115*(1+'1. Inputs'!J$68)
A116: BP&C subscription revenue | F116: =F114*F115 | G116: =G114*G115 | H116: =H114*H115 | I116: =I114*I115 | J116: =J114*J115
A117: Creative subscription revenue | F117: =$D85*(1+'1. Inputs'!F$69+'1. Inputs'!F$70+'1. Inputs'!F$50) | G117: =F117*(1+'1. Inputs'!G$69+'1. Inputs'!G$70+'1. Inputs'!G$50) | H117: =G117*(1+'1. Inputs'!H$69+'1. Inputs'!H$70+'1. Inputs'!H$50) | I117: =H117*(1+'1. Inputs'!I$69+'1. Inputs'!I$70+'1. Inputs'!I$50) | J117: =I117*(1+'1. Inputs'!J$69+'1. Inputs'!J$70+'1. Inputs'!J$50)
A118: Digital Experience subscription revenue | F118: =$D86*(1+'1. Inputs'!F$71) | G118: =F118*(1+'1. Inputs'!G$71) | H118: =G118*(1+'1. Inputs'!H$71) | I118: =H118*(1+'1. Inputs'!I$71) | J118: =I118*(1+'1. Inputs'!J$71)
A119: Semrush revenue | F119: ='1. Inputs'!F$52 | G119: ='1. Inputs'!G$52 | H119: ='1. Inputs'!H$52 | I119: ='1. Inputs'!I$52 | J119: ='1. Inputs'!J$52 | M119: SEVERE takes the lower override path on sheet 1 §E (forecast_earnings_calcs.py §9).
...

Sheet 3. Terminal Value and SOTP
A1: Adobe Inc. (ADBE) — TERMINAL VALUE AND SUM-OF-THE-PARTS VALUATION
A2: Value = PV(forecast owners' earnings) + PV(terminal value) + standalone assets − all debt-like items, divided by TODAY's diluted share count. The valuation is trading-price blind: Adobe's share price and market capitalisation are not an input anywhere on this sheet (valuation.md §0, §2).
A3: CONTENTS: §A Headline sum of the parts | §B Terminal value by scenario | §C Gordon cross-check on the terminal multiples | §D Discounting | §E Full valuation by scenario | §F Equity bridge | §G Sensitivity | §H Checks
A5: §A. HEADLINE — SUM OF THE PARTS, PROBABILITY-WEIGHTED
A7: Part 1 PV of explicit-period owners' earnings, FY2026E-FY2030E (t=0..4) | B7: =F51 | H7: Detail in §E. Each scenario's own owners'-earnings path from sheet 2 §7, discounted at the rate on sheet 1.
A8: Part 2 PV of terminal value at FY2030 year-end (t=4) | B8: =F52 | H8: Detail in §B and §E.
A9: = ENTERPRISE VALUE | B9: =B7+B8 | H9: An ENTERPRISE value, because owners' earnings are unlevered: interest expense and interest income sit below the operating line and are excluded (terminal_value.md §2).
A10: Part 3 + Standalone assets (excess cash and short-term investments) | B10: =B68
A11: Part 4 − Total debt-like items | B11: =-B75 | H11: Funded debt + operating leases + the PV of off-balance-sheet hosting commitments. Detail and alternative conventions in §F and §G(ii).
A12: = EQUITY VALUE | B12: =B9+B10+B11
A13: ÷ diluted shares outstanding (M) | B13: ='1. Inputs'!$B$32
A14: = INTRINSIC VALUE PER DILUTED SHARE | B14: =B12/B13 | H14: valuation.md §1. The probability-weighted headline. §E shows the same walk for each scenario separately — the range is roughly 4.7x from least to most favourable, which is the honest measure of how open the question is.
A16: memo: terminal value as % of enterprise value | B16: =B8/B9 | H16: ~72%. The answer is dominated by the terminal multiple, not by the five-year forecast. terminal_value.md §1 also flags that 38% of the probability-weighted terminal value comes from the 20%-probability bull case.
A18: §B. TERMINAL VALUE AT FY2030 YEAR-END, BY SCENARIO (undiscounted, enterprise basis)
A20: ($M unless noted) | B20: SEVERE | C20: BEAR | D20: BASE | E20: BULL | F20: WEIGHTED
A21: Probability | B21: ='1. Inputs'!$B$17 | C21: ='1. Inputs'!$B$18 | D21: ='1. Inputs'!$B$19 | E21: ='1. Inputs'!$B$20 | F21: =SUM(B21:E21) | H21: From sheet 1 §B. The WEIGHTED column here is the check that they sum to 100%.
A22: FY2030E owners' earnings | B22: ='2. Owners Earnings'!J178 | C22: ='2. Owners Earnings'!J179 | D22: ='2. Owners Earnings'!J180 | E22: ='2. Owners Earnings'!J181 | F22: ='2. Owners Earnings'!J182 | H22: Sheet 2 §7 — the end point of each scenario's owners'-earnings path.
A23: Terminal multiple (x FY2030E owners' earnings) | B23: ='1. Inputs'!$C$17 | C23: ='1. Inputs'!$C$18 | D23: ='1. Inputs'!$C$19 | E23: ='1. Inputs'!$C$20 | F23: =F25/F22 | H23: ANALYST JUDGMENT (terminal_value.md §6.2), cross-checked in §C. Each multiple is applied to ITS OWN scenario's earnings; a multiple is never applied to blended earnings. The WEIGHTED cell is therefore an OUTPUT — the multiple implied by the weighted terminal value divided by the weighted FY2030E earnings ( = 15.3x, terminal_value.md §1). Note this is NOT the probability-weighted average of the four multiples, which is 14.2x: the higher-earnings scenarios also carry the higher multiples, so the implied multiple exceeds the simple mean.
A24: memo: probability-weighted AVERAGE of the four multiples | F24: =B21*B23+C21*C23+D21*D23+E21*E23 | H24: Shown only to make the distinction above explicit. This figure is NOT used anywhere in the valuation.
A25: TERMINAL VALUE at FY2030 year-end | B25: =B23*B22 | C25: =C23*C22 | D25: =D23*D22 | E25: =E23*E22 | F25: =B21*B25+C21*C25+D21*D25+E21*E25 | H25: terminal_value.md §1: $42.2bn / $89.2bn / $161.2bn / $286.8bn, weighted $150.4bn. Applying a single 15x to weighted earnings instead would give $147.5bn, 'only 1.9% away' — the weighting method is not doing the work.
A26: share of the weighted terminal value | B26: =B21*B25/$F25 | C26: =C21*C25/$F25 | D26: =D21*D25/$F25 | E26: =E21*E25/$F25 | H26: terminal_value.md §1. Note the bull case supplies ~38% of the weighted terminal value on a 20% probability — the single largest concentration of judgment in the valuation.
A28: §C. CROSS-CHECK ON THE TERMINAL MULTIPLES — GORDON PERPETUITY GRID
A29: Value / owners' earnings = (1 − g / ROIC) / (r − g). The (1 − g/ROIC) term is the reinvestment drag: growth is not free, it must be funded out of earnings. terminal_value.md §6.1 runs this grid at ROIC ~70% (sheet 1 §A) and rejects a third-party 11.53% WACC as too high, using an 8-10% band instead. This grid is a SANITY CHECK on the judgment multiples in §B — it does not feed the valuation.
A31: perpetual growth g \ discount rate r | B31: 0.08 | C31: 0.09 | D31: 0.1 | E31: 0.11
A32: -0.03 | B32: =(1-$A32/'1. Inputs'!$B$13)/(B$31-$A32) | C32: =(1-$A32/'1. Inputs'!$B$13)/(C$31-$A32) | D32: =(1-$A32/'1. Inputs'!$B$13)/(D$31-$A32) | E32: =(1-$A32/'1. Inputs'!$B$13)/(E$31-$A32) | H32: Read against §B: SEVERE 7x sits below the g=-3% row; BEAR 11x between g=0% and g=1%; BASE 15x just under the g=3%, r=9% cell (16.0x); BULL 22x just above g=4%, r=8.5%. Each judgment multiple is therefore internally consistent with a plausible (g, r) pair rather than picked freehand.
A33: 0 | B33: =(1-$A33/'1. Inputs'!$B$13)/(B$31-$A33) | C33: =(1-$A33/'1. Inputs'!$B$13)/(C$31-$A33) | D33: =(1-$A33/'1. Inputs'!$B$13)/(D$31-$A33) | E33: =(1-$A33/'1. Inputs'!$B$13)/(E$31-$A33)
A34: 0.01 | B34: =(1-$A34/'1. Inputs'!$B$13)/(B$31-$A34) | C34: =(1-$A34/'1. Inputs'!$B$13)/(C$31-$A34) | D34: =(1-$A34/'1. Inputs'!$B$13)/(D$31-$A34) | E34: =(1-$A34/'1. Inputs'!$B$13)/(E$31-$A34)
A35: 0.02 | B35: =(1-$A35/'1. Inputs'!$B$13)/(B$31-$A35) | C35: =(1-$A35/'1. Inputs'!$B$13)/(C$31-$A35) | D35: =(1-$A35/'1. Inputs'!$B$13)/(D$31-$A35) | E35: =(1-$A35/'1. Inputs'!$B$13)/(E$31-$A35)
A36: 0.03 | B36: =(1-$A36/'1. Inputs'!$B$13)/(B$31-$A36) | C36: =(1-$A36/'1. Inputs'!$B$13)/(C$31-$A36) | D36: =(1-$A36/'1. Inputs'!$B$13)/(D$31-$A36) | E36: =(1-$A36/'1. Inputs'!$B$13)/(E$31-$A36)
A37: 0.04 | B37: =(1-$A37/'1. Inputs'!$B$13)/(B$31-$A37) | C37: =(1-$A37/'1. Inputs'!$B$13)/(C$31-$A37) | D37: =(1-$A37/'1. Inputs'!$B$13)/(D$31-$A37) | E37: =(1-$A37/'1. Inputs'!$B$13)/(E$31-$A37)
A39: Peer anchors at 31 Aug 2026 (fetched_docs/peer_multiples_compare_2026.md, terminal_value.md §5): mature large-cap software trailing P/E median 27.2x (MSFT 28.6x, SAP 28.8x, ORCL 25.9x, CRM 23.7x, INTU 21.8x, ADSK 33.8x); ex-growth / disruption-discounted median 18.8x (DBX 19.7x, GEN 18.0x, ZM 9.0x, DOCU 41.6x). ADBE itself trades at 16.7x trailing owners' earnings, a 59% de-rating from its own FY2021-FY2025 median of 40.9x. Peer P/Es are read directly against owners'-earnings multiples because TTM owners' earnings ($7,490M) sit only 3.6% above TTM GAAP net income ($7,230M) — terminal_value.md §2.
A41: §D. DISCOUNTING
A42: valuation.md §2: the current fiscal year is t=0 and is NOT discounted. As of the 1 Sep 2026 valuation date Adobe is inside FY2026, so FY2026E = t=0. The terminal value is the value of the business AT THE END of FY2030, realised at the same moment as the FY2030 flow, so it is discounted at the same t=4 factor — not t=5.
A44: ($M unless noted) | B44: FY2026E | C44: FY2027E | D44: FY2028E | E44: FY2029E | F44: FY2030E
A45: t (years discounted) | B45: 0 | C45: 1 | D45: 2 | E45: 3 | F45: 4
A46: Discount factor = 1 / (1 + r)^t | B46: =1/(1+'1. Inputs'!$B$9)^B45 | C46: =1/(1+'1. Inputs'!$B$9)^C45 | D46: =1/(1+'1. Inputs'!$B$9)^D45 | E46: =1/(1+'1. Inputs'!$B$9)^E45 | F46: =1/(1+'1. Inputs'!$B$9)^F45 | H46: r is the single input at sheet 1 cell B9. At 15% the factors are 1.0000 / 0.8696 / 0.7561 / 0.6575 / 0.5718.
A48: §E. FULL VALUATION BY SCENARIO — the four 'parts' behind the headline
A50: ($M unless noted) | B50: SEVERE | C50: BEAR | D50: BASE | E50: BULL | F50: WEIGHTED
A51: Part 1 PV of owners' earnings, FY2026E-FY2030E | B51: =SUMPRODUCT('2. Owners Earnings'!$F$178:$J$178,$B46:$F46) | C51: =SUMPRODUCT('2. Owners Earnings'!$F$179:$J$179,$B46:$F46) | D51: =SUMPRODUCT('2. Owners Earnings'!$F$180:$J$180,$B46:$F46) | E51: =SUMPRODUCT('2. Owners Earnings'!$F$181:$J$181,$B46:$F46) | F51: =SUMPRODUCT('2. Owners Earnings'!$F$182:$J$182,$B46:$F46) | H51: Each scenario's own owners'-earnings path (sheet 2 §7) times the discount factors in §D.
A52: Part 2 PV of terminal value (discounted at t=4) | B52: =B25*$F46 | C52: =C25*$F46 | D52: =D25*$F46 | E52: =E25*$F46 | F52: =F25*$F46 | H52: The terminal values from §B brought back four years.
A53: = ENTERPRISE VALUE | B53: =B51+B52 | C53: =C51+C52 | D53: =D51+D52 | E53: =E51+E52 | F53: =F51+F52
A54: Part 3 + Standalone assets | B54: =$B68 | C54: =$B68 | D54: =$B68 | E54: =$B68 | F54: =$B68
A55: Part 4 − Total debt-like items | B55: =-$B75 | C55: =-$B75 | D55: =-$B75 | E55: =-$B75 | F55: =-$B75 | H55: Identical in every scenario: the bridge is struck on today's balance sheet, not forecast forward. terminal_value.md §9 notes FY2030 net debt should stay ~1% of a ~$150bn EV IF the buyback throttles to ~90% of owners' earnings; at the FY2024-25 pace of ~1.5x, 'the equity bridge stops being immaterial'. That risk is NOT modelled here.
A56: = EQUITY VALUE | B56: =B53+B54+B55 | C56: =C53+C54+C55 | D56: =D53+D54+D55 | E56: =E53+E54+E55 | F56: =F53+F54+F55
A57: ÷ diluted shares (M) | B57: ='1. Inputs'!$B$32 | C57: ='1. Inputs'!$B$32 | D57: ='1. Inputs'!$B$32 | E57: ='1. Inputs'!$B$32 | F57: ='1. Inputs'!$B$32
A58: = INTRINSIC VALUE PER DILUTED SHARE | B58: =B56/B57 | C58: =C56/C57 | D58: =D56/D57 | E58: =E56/E57 | F58: =F56/F57 | H58: valuation.md §1: ~$104 / ~$183 / ~$298 / ~$487, weighted ~$278.
A59: memo: terminal value as % of enterprise value | B59: =B52/B53 | C59: =C52/C53 | D59: =D52/D53 | E59: =E52/E53 | F59: =F52/F53
A60: cross-check: probability-weighted average of the four per-share values | F60: =B21*B58+C21*C58+D21*D58+E21*E58 | H60: Discounting is linear, so this MUST equal the WEIGHTED column above. A real internal-consistency check: it confirms the cash-flow stream and the terminal value are weighted on the same probabilities and combined exactly once. valuation.md §2.1 reports the two agree 'to the cent'.
A61: difference (must be 0) | F61: =F60-F58
A63: §F. THE EQUITY BRIDGE — standalone assets and all debt-like items (Q2 FY2026 balance sheet, 29 May 2026)
A65: Cash and cash equivalents | B65: ='1. Inputs'!$B$24
A66: Short-term investments | B66: ='1. Inputs'!$B$25
A67: − operating cash need (2% of TTM revenue) | B67: =-'1. Inputs'!$B$12*'2. Owners Earnings'!$E$11 | H67: owners_earnings_and_roic.md §4: 'Adobe collects in advance and runs negative working capital, so its genuine operating cash requirement is small. ... This is an assumption, not a sourced figure.' 2% of TTM revenue = ~$504M.
A68: = STANDALONE ASSETS | B68: =SUM(B65:B67)
A70: Debt, current (incl. commercial paper), carrying value | B70: ='1. Inputs'!$B$26
A71: Debt, long-term, carrying value | B71: ='1. Inputs'!$B$27
A72: Operating lease liabilities, current | B72: ='1. Inputs'!$B$28
A73: Operating lease liabilities, long-term | B73: ='1. Inputs'!$B$29
A74: Off-balance-sheet hosting purchase obligations, PV @ 5% | B74: ='1. Inputs'!$B$43 | H74: A DISCLOSED JUDGMENT CALL, and the largest single swing in the bridge. The brief lists off-balance-sheet commitments as debt, and the same rule is applied symmetrically to operating leases. §G(ii) prices the alternatives.
A75: = TOTAL DEBT-LIKE ITEMS | B75: =SUM(B70:B74)
A76: Net standalone assets less debt | B76: =B68-B75 | H76: ~−$8.2bn, roughly $20/share of drag. NOT included: legal contingencies — Adobe is 'unable to estimate a reasonably possible financial loss or range of financial loss, if any' on the securities class action and derivative actions (Q2 FY2026 10-Q Note 13). That is flagged as an UNQUANTIFIED RISK, not a zero. No defined-benefit pension is disclosed.
A78: §G. SENSITIVITY — the three assumptions that actually move the answer
A80: (i) Discount rate (probability-weighted path throughout)
A81: Discount rate | B81: PV(OE) | C81: PV(TV) | D81: Enterprise value | E81: Value / share | F81: TV % of EV | H81: The discount rate is a STATED variable, not a fitted one (valuation.md §5.2). A 5-point change moves the per-share answer by roughly 14-16% — large, but not large enough to change the sign of the conclusion on its own.
A82: 0.1 | B82: =SUMPRODUCT('2. Owners Earnings'!$F$182:$J$182,1/(1+$A82)^(COLUMN('2. Owners Earnings'!$F$182:$J$182)-COLUMN('2. Owners Earnings'!$F$182))) | C82: =$F25/(1+$A82)^4 | D82: =B82+C82 | E82: =(D82+$B68-$B75)/'1. Inputs'!$B$32 | F82: =C82/D82
A83: 0.125 | B83: =SUMPRODUCT('2. Owners Earnings'!$F$182:$J$182,1/(1+$A83)^(COLUMN('2. Owners Earnings'!$F$182:$J$182)-COLUMN('2. Owners Earnings'!$F$182))) | C83: =$F25/(1+$A83)^4 | D83: =B83+C83 | E83: =(D83+$B68-$B75)/'1. Inputs'!$B$32 | F83: =C83/D83
A84: 0.15 | B84: =SUMPRODUCT('2. Owners Earnings'!$F$182:$J$182,1/(1+$A84)^(COLUMN('2. Owners Earnings'!$F$182:$J$182)-COLUMN('2. Owners Earnings'!$F$182))) | C84: =$F25/(1+$A84)^4 | D84: =B84+C84 | E84: =(D84+$B68-$B75)/'1. Inputs'!$B$32 | F84: =C84/D84
A85: 0.175 | B85: =SUMPRODUCT('2. Owners Earnings'!$F$182:$J$182,1/(1+$A85)^(COLUMN('2. Owners Earnings'!$F$182:$J$182)-COLUMN('2. Owners Earnings'!$F$182))) | C85: =$F25/(1+$A85)^4 | D85: =B85+C85 | E85: =(D85+$B68-$B75)/'1. Inputs'!$B$32 | F85: =C85/D85
A86: 0.2 | B86: =SUMPRODUCT('2. Owners Earnings'!$F$182:$J$182,1/(1+$A86)^(COLUMN('2. Owners Earnings'!$F$182:$J$182)-COLUMN('2. Owners Earnings'!$F$182))) | C86: =$F25/(1+$A86)^4 | D86: =B86+C86 | E86: =(D86+$B68-$B75)/'1. Inputs'!$B$32 | F86: =C86/D86
A88: (ii) Which items belong in the debt bridge (a disclosed judgment call)
A89: Convention | B89: Total debt-like | C89: Value / share
A90: Headline: funded debt + leases + hosting (the brief, literally) | B90: =$B75 | C90: =($F53+$B68-B90)/'1. Inputs'!$B$32 | H90: The published headline. valuation.md §3, after verifier objection 1 required leases and hosting to be treated symmetrically.
A91: Funded debt + leases only, hosting excluded | B91: =$B75-$B74 | C91: =($F53+$B68-B91)/'1. Inputs'!$B$32
A92: Funded debt only, leases and hosting both excluded | B92: =SUM($B70:$B71) | C92: =($F53+$B68-B92)/'1. Inputs'!$B$32 | H92: Full range across the three conventions is ~$16.74/share, a 6.0% spread — material but not decisive.
A94: (iii) Terminal multiples — all four scaled together
A95: Scaling applied to every scenario multiple | B95: Weighted TV | C95: PV of TV | D95: Enterprise value | E95: Value / share | H95: Terminal value is linear in the multiple, so a uniform scaling passes straight through. terminal_value.md §8 gives a defensible aggregate range of $120-180bn, which is the x0.8 to x1.2 band below. Because terminal value is ~72% of enterprise value, this is the single largest sensitivity on the sheet.
A96: 0.8 | B96: =$A96*$F25 | C96: =B96*$F46 | D96: =$F51+C96 | E96: =(D96+$B68-$B75)/'1. Inputs'!$B$32
A97: 0.9 | B97: =$A97*$F25 | C97: =B97*$F46 | D97: =$F51+C97 | E97: =(D97+$B68-$B75)/'1. Inputs'!$B$32
A98: 1 | B98: =$A98*$F25 | C98: =B98*$F46 | D98: =$F51+C98 | E98: =(D98+$B68-$B75)/'1. Inputs'!$B$32
A99: 1.1 | B99: =$A99*$F25 | C99: =B99*$F46 | D99: =$F51+C99 | E99: =(D99+$B68-$B75)/'1. Inputs'!$B$32
A100: 1.2 | B100: =$A100*$F25 | C100: =B100*$F46 | D100: =$F51+C100 | E100: =(D100+$B68-$B75)/'1. Inputs'!$B$32
A102: §H. CHECKS AGAINST THE PUBLISHED WORK PRODUCTS
B104: Model | C104: Published | D104: Diff
A105: Terminal value, SEVERE ($M) | B105: =B25 | C105: 42154 | D105: =B105-C105 | H105: terminal_value.md §1
A106: Terminal value, BEAR ($M) | B106: =C25 | C106: 89155 | D106: =B106-C106 | H106: terminal_value.md §1
A107: Terminal value, BASE ($M) | B107: =D25 | C107: 161175 | D107: =B107-C107 | H107: terminal_value.md §1
A108: Terminal value, BULL ($M) | B108: =E25 | C108: 286770 | D108: =B108-C108 | H108: terminal_value.md §1
A109: Probability-weighted terminal value ($M) | B109: =F25 | C109: 150436 | D109: =B109-C109 | H109: terminal_value.md §1 / valuation.md §2.1
A110: Implied weighted terminal multiple | B110: =F23 | C110: 15.3 | D110: =B110-C110 | H110: terminal_value.md §1
A111: PV of owners' earnings, weighted ($M) | B111: =F51 | C111: 33057 | D111: =B111-C111 | H111: valuation.md §2.2
A112: PV of terminal value, weighted ($M) | B112: =F52 | C112: 86012 | D112: =B112-C112 | H112: valuation.md §2.2
A113: Enterprise value, weighted ($M) | B113: =F53 | C113: 119069 | D113: =B113-C113 | H113: valuation.md §2.2
A114: Standalone assets ($M) | B114: =B68 | C114: 5122 | D114: =B114-C114 | H114: valuation.md §3
A115: Total debt-like items ($M) | B115: =B75 | C115: 13324 | D115: =B115-C115 | H115: valuation.md §3
A116: Equity value, weighted ($M) | B116: =F56 | C116: 110867 | D116: =B116-C116 | H116: valuation.md §3
A117: Diluted shares (M) | B117: ='1. Inputs'!$B$32 | C117: 399.1 | D117: =B117-C117 | H117: valuation.md §3
A118: INTRINSIC VALUE PER SHARE — SEVERE | B118: =B58 | C118: 103.77 | D118: =B118-C118 | H118: valuation.md §1
A119: INTRINSIC VALUE PER SHARE — BEAR | B119: =C58 | C119: 182.59 | D119: =B119-C119 | H119: valuation.md §1
A120: INTRINSIC VALUE PER SHARE — BASE | B120: =D58 | C120: 297.71 | D120: =B120-C120 | H120: valuation.md §1
A121: INTRINSIC VALUE PER SHARE — BULL | B121: =E58 | C121: 487.47 | D121: =B121-C121 | H121: valuation.md §1
...
