Workbook

Sheet Inputs
B1: NamSys Inc. (TSXV: CTZ) -- valuation model INPUTS
B2: All Canadian dollars. Fiscal year ends October 31. Every cell shaded BEIGE with BLUE BOLD text is a hard-coded input; change it and the whole model re-computes. Black cells are formulas. Column Q carries the source for each input.
B4: LEGEND: | C4: input | D4: = editable input
B6: 1. VALUATION ASSUMPTIONS (VAL s1)
B7: Discount rate (r) | C7: 0.1 | Q7: VAL s1 DISCOUNT_RATE -- set by the brief, not independently derived; sensitised on the Valuation sheet
B8: Diluted shares outstanding | C8: 27459593 | Q8: MDQ2 line 114: weighted-average diluted shares, 3 months ended Apr 30 2026
B9: Cross-check: H1 FY2026 diluted shares | C9: 27498422 | Q9: FSQ2 line 85: six months ended Apr 30 2026 (used only as a cross-check)
B10: Cash at April 30, 2026 | C10: 940082 | Q10: FSQ2 balance sheet / OE s4
B11: Short-term investments at April 30, 2026 | C11: 6425965 | Q11: FSQ2 balance sheet (cashable GICs) / OE s4
B12: Debt | C12: 0 | Q12: OE s2 pt1, quoting FY2025 MD&A: 'the Company has no debt outstanding'
B13: Contingent employee termination commitment | C13: 1100000 | Q13: FS25 Note 13 / OE s3.1 -- payable only on termination without cause
B14: Treat that commitment as debt? (1 = yes, 0 = no) | C14: 0 | Q14: VAL s3.3/s5 -- base case is 0 (contingent, not a certain obligation)
B15: = Standalone assets (cash + short-term investments) | C15: =$C$10+$C$11 | Q15: VAL s3.3 CASH_AND_STI_APR26 = 940,082 + 6,425,965
B16: = Total debt-like deduction | C16: =$C$12+$C$14*$C$13
B17: Scenario shown on the 'Owners Earnings' sheet | C17: 1 | D17: 1 = Base, 2 = Bull, 3 = Bear (no cost response), 4 = Bear (right-sizes)
B19: 2. TERMINAL MULTIPLE ON FY2030E OWNERS' EARNINGS (TV s5/s6)
B20: Low end of defensible range | C20: 9 | Q20: TV s6 MULT_LOW -- mature low-growth microcap software cluster (TV s3)
B21: Base case | C21: 12 | Q21: TV s6 MULT_BASE -- high quality (99% recurring, ~40% margin, no debt) offset by 37-39% top-3 concentration (TV s3.1/s3.2)
B22: High end of defensible range | C22: 15 | Q22: TV s6 MULT_HIGH -- high-margin microcap software / take-private cluster
B23: Bear scenarios (both variants) | C23: 8 | Q23: TV s6 diagonal -- the multiple co-moves with the scenario
B24: Scenario-consistent multiple: Bull | C24: =$C$22 | Q24: TV s6: bull pairs with 15x
B26: 3. NORMALISATION AND TAX CONSTANTS (OE s2)
B27: Statutory tax rate | C27: 0.265 | Q27: MDA25: 'The basic rate of 26.50% was applied'
B28: Normalised bad debt expense (4-yr average) | C28: =AVERAGE(C37:F37) | Q28: OE s2.1 NORM_BAD_DEBT -- simple average of reported FY2022-FY2025 bad debt expense
B29: Normalised share-based compensation (FY2023-FY2025 avg) | C29: =AVERAGE(D38:F38) | Q29: OE s2.1 NORM_SBC -- average of the only three years with a live grant; cross-checks to the Dec-2022 grant fair value of $357,566 over 3 years = $119,189
B30: Forecast other permanent tax difference, per year | C30: 1300 | Q30: FC PERM_DIFF -- Note 9 unexplained residual, FY2025 $1,385 / TTM $1,162 (OE s2.2e); held flat forward
B32: 4. REPORTED HISTORICAL FINANCIALS (all from primary_sources)
B33: TTM Apr-26 = FY2025 + H1 FY2026 - H1 FY2025 (OE script, TTM Period)
C34: FY2022A | D34: FY2023A | E34: FY2024A | F34: FY2025A | M34: H1 FY2025 | N34: H1 FY2026 | O34: TTM Apr-26
B35: Revenue | C35: 5394781 | D35: 6093020 | E35: 6840146 | F35: 7891605 | M35: 3951863 | N35: 4267406 | O35: =F35+N35-M35 | Q35: FS23/FS25/FSQ2 statements of operations
B36: Operating income (reported) | C36: 1753157 | D36: 2107434 | E36: 2572018 | F36: 3146476 | M36: 1626795 | N36: 1779560 | O36: =F36+N36-M36 | Q36: FS23/FS25/FSQ2 -- after bad debt, SBC and depreciation
B37: Bad debt expense (inside operating income) | C37: 2546 | D37: 23004 | E37: 0 | F37: 51330 | M37: 50746 | N37: 0 | O37: =F37+N37-M37 | Q37: FS23/FS24/FS25/FSQ2 expense note
B38: Share-based compensation (inside operating income) | C38: 0 | D38: 191468 | E38: 114174 | F38: 47030 | M38: 27020 | N38: 4894 | O38: =F38+N38-M38 | Q38: FS25 Note 6 / FSQ2 Note 6
B39: Depreciation of property and equipment | C39: 12028 | D39: 7191 | E39: 7023 | F39: 7465 | M39: 3449 | N39: 3623 | O39: =F39+N39-M39 | Q39: FS25 Note 4. FY2022 excludes $10,768 of right-of-use depreciation: that is a real rent cost, not a non-economic charge (OE s2.1)
B40: Purchase of property and equipment (maintenance capex) | C40: 9311 | D40: 4982 | E40: 8259 | F40: 9661 | M40: 3998 | N40: 3595 | O40: =F40+N40-M40 | Q40: FS23/FS25/FSQ2 statements of cash flows -- investing activities
B41: 'Adjustments to determine taxable income' (Note 9) | C41: 1091 | D41: 73248 | E41: 33269 | F41: 13848 | M41: 7932 | N41: 1846 | O41: =F41+N41-M41 | Q41: FS23/FS24/FS25 Note 9 and FSQ2 Note 9 tax-rate reconciliation
B42: Memo: reported net income | C42: 1394440 | D42: 1614875 | E42: 2090475 | F42: 2486109 | M42: 1259346 | N42: 1312064 | O42: =F42+N42-M42 | Q42: FS23/FS25/FSQ2
B43: Memo: interest income (EXCLUDED from owners' earnings) | C43: 5812 | D43: 195112 | E43: 291840 | F43: 265771 | M43: 132073 | N43: 111013 | O43: =F43+N43-M43 | Q43: FS23/FS25/FSQ2 -- excluded per OE s2.2(a); the portfolio is added separately
B44: Memo: FX gain / (loss) (normalised to nil) | C44: 139768 | D44: -5780 | E44: 25590 | F44: -10945 | M44: -34680 | N44: -102941 | O44: =F44+N44-M44 | Q44: FS23/FS25/FSQ2 -- below operating income, normalised to nil (OE s2)
B45: Memo: cash flow from operating activities | C45: 962018 | D45: 1659749 | E45: 2508076 | F45: 2196505 | M45: 1223129 | N45: 1497265 | O45: =F45+N45-M45 | Q45: FS23/FS25/FSQ2. The H1 FY2026 figure of 1,497,265 is the cash already inside the Apr-30-26 balance -- VAL s3.1 nets it out of the t=0 flow
B47: 5. FY2025 REVENUE BASE AND GEOGRAPHY (the forecast starting point, FC s2/s3)
B48: FY2025 revenue -- US | C48: 5979328 | Q48: FS25 Note 7 geographic revenue
B49: FY2025 revenue -- Mexico | C49: 846155 | Q49: FS25 Note 7 geographic revenue
B50: FY2025 revenue -- Canada | C50: 286682 | Q50: FS25 Note 7 geographic revenue
B51: FY2025 revenue -- Dominican Republic | C51: 275378 | Q51: FS25 Note 7 geographic revenue
B52: FY2025 revenue -- Puerto Rico | C52: 262573 | Q52: FS25 Note 7 geographic revenue
B53: FY2025 revenue -- Other | C53: 241489 | Q53: FS25 Note 7 geographic revenue
B54: Check: geographic total less reported FY2025 revenue | C54: =SUM(C48:C53)-F35 | Q54: must be zero
B55: USD/CAD average rate, FY2025 | C55: 1.4009 | Q55: Knowledge Store ID 11 -- Bank of Canada monthly-average USD/CAD, FY2025 fiscal-year average
B56: Legacy largest-customer share of FY2025 revenue | C56: 0.159 | Q56: FS25 Note 7: largest customer 15.9% of revenue. FC s1b shows by elimination that this account must sit in the US country bucket
B57: Derived FY2025 starting buckets (FC SECTION 4 'START'). ~96% of revenue is invoiced in USD (FSQ2 Note 11), so the non-Canadian buckets are carried in USD and translated each year.
B58: US base excluding the legacy account (USD) | C58: =(C48-$C$56*F35)/$C$55
B59: Legacy largest US account (USD) | C59: =$C$56*F35/$C$55
B60: Mexico -- inferred single account (USD) | C60: =C49/$C$55
B61: Other international: DR + PR + Other (USD) | C61: =(C51+C52+C53)/$C$55
B62: Canada (CAD -- not translated) | C62: =C50
B64: 6. FY2025 COST BASE (the forecast cost starting point, FC s4)
B65: Cost of sales (total) | C65: 2813196 | Q65: FS25 statement of operations
B66: of which Note 14 compensation | C66: 1739266 | Q66: FS25 Note 14
B67: Selling expense (total) | C67: 714618 | Q67: FS25 statement of operations
B68: of which Note 14 compensation | C68: 486478 | Q68: FS25 Note 14
B69: General and administration (total) | C69: 1165985 | Q69: FS25 statement of operations
B70: of which Note 14 compensation | C70: 555762 | Q70: FS25 Note 14
B71: Average headcount, FY2025 | C71: 17 | Q71: AM25: 'stable at 17 employees'. AM26: 'up to 21 employees today' (Apr 2026)
B72: = Cash compensation (Note 14 total less reported SBC) | C72: =C66+C68+C70-F38 | Q72: FC CASH_COMP_FY2025 = 2,781,506 - 47,030
B73: = Cash compensation per head | C73: =$C$72/C71 | Q73: FC COMP_PER_HEAD_FY2025 -- the unit cost driven forward by headcount x wage inflation
B74: = Non-compensation cost of sales (hosting, support, etc.) | C74: =C65-C66 | Q74: FC COS_NONCOMP_FY2025
B75: = Non-compensation selling | C75: =C67-C68 | Q75: FC SELL_NONCOMP_FY2025
B76: = Non-compensation G&A | C76: =C69-C70 | Q76: FC GA_NONCOMP_FY2025
B77: Check: rebuilt FY2025 operating income less reported | C77: =(F35-($C$72+F38+$C$74+$C$76+$C$75+F37))-F36 | Q77: FC s4b back-test: must be zero -- the cost build reproduces reported FY2025 operating income exactly
B79: 7. FORECAST DRIVERS BY SCENARIO (FC s4 SCENARIOS; all cells editable)
B80: SCENARIO: Base | Q80: FC s4/s5 Base: legacy US account -20%/yr, Mexico rollout decelerates, headcount to 26 by FY2030E
G81: FY2026E | H81: FY2027E | I81: FY2028E | J81: FY2029E | K81: FY2030E
B82: US ex-legacy revenue growth (constant currency, USD) | G82: 0.13 | H82: 0.11 | I82: 0.095 | J82: 0.08 | K82: 0.07
B83: Legacy largest US account growth (USD) | G83: -0.2 | H83: -0.2 | I83: -0.2 | J83: -0.2 | K83: -0.2
B84: Mexico account growth (USD) | G84: 0.48 | H84: 0.18 | I84: 0.1 | J84: 0.07 | K84: 0.05
B85: Other international growth (USD) | G85: 0.09 | H85: 0.13 | I85: 0.15 | J85: 0.15 | K85: 0.14
B86: Canada growth (CAD) | G86: 0.05 | H86: 0.05 | I86: 0.05 | J86: 0.05 | K86: 0.05
B87: USD/CAD average rate | G87: 1.386 | H87: 1.39 | I87: 1.39 | J87: 1.39 | K87: 1.39
B88: Average headcount | G88: 19.8 | H88: 22.5 | I88: 24 | J88: 25 | K88: 26
B89: Wage inflation (per year, compounding) | G89: 0.035 | H89: 0.035 | I89: 0.035 | J89: 0.035 | K89: 0.035
B90: Non-comp cost-of-sales elasticity to revenue growth | G90: 0.85 | H90: 0.85 | I90: 0.85 | J90: 0.85 | K90: 0.85
B91: Non-comp selling expense, FY2026E level ($) | G91: 150000 | Q91: FC s4: non-comp selling is reset to $150,000 in FY2026E from the $228,140 FY2025A actual (a -34.3% step), then compounds at the scenario rate below. H1 FY2026 actual was $65,396, cut for 'lower travel and trade show attendance costs' (MDQ2); the forecast assumes management re-spends on the international strategy it is relying on
B92: Non-comp selling expense, growth per year thereafter | G92: 0.1 | Q92: FC s4 / FC md s4: 10%/yr. This is the only cost line whose growth rate differs by scenario, and deliberately so -- it is pure discretionary growth investment (MDA25 attributes FY2025's 61.6% selling-expense jump to a new European business-development position and trade-show travel)
B93: Non-comp G&A growth | G93: 0.035 | H93: 0.035 | I93: 0.035 | J93: 0.035 | K93: 0.035
B95: SCENARIO: Bull | Q95: FC s4/s5 Bull: legacy stabilises, a 2nd Mexico-sized international account lands from FY2028E
G96: FY2026E | H96: FY2027E | I96: FY2028E | J96: FY2029E | K96: FY2030E
B97: US ex-legacy revenue growth (constant currency, USD) | G97: 0.14 | H97: 0.13 | I97: 0.12 | J97: 0.11 | K97: 0.1
B98: Legacy largest US account growth (USD) | G98: -0.15 | H98: -0.08 | I98: -0.05 | J98: -0.05 | K98: -0.05
B99: Mexico account growth (USD) | G99: 0.5 | H99: 0.25 | I99: 0.15 | J99: 0.1 | K99: 0.08
B100: Other international growth (USD) | G100: 0.12 | H100: 0.2 | I100: 0.3 | J100: 0.28 | K100: 0.24
B101: Canada growth (CAD) | G101: 0.06 | H101: 0.06 | I101: 0.06 | J101: 0.06 | K101: 0.06
B102: USD/CAD average rate | G102: 1.386 | H102: 1.39 | I102: 1.39 | J102: 1.39 | K102: 1.39
B103: Average headcount | G103: 19.8 | H103: 22 | I103: 23 | J103: 24 | K103: 25
B104: Wage inflation (per year, compounding) | G104: 0.03 | H104: 0.03 | I104: 0.03 | J104: 0.03 | K104: 0.03
B105: Non-comp cost-of-sales elasticity to revenue growth | G105: 0.75 | H105: 0.75 | I105: 0.75 | J105: 0.75 | K105: 0.75
B106: Non-comp selling expense, FY2026E level ($) | G106: 150000 | Q106: FC s4: non-comp selling is reset to $150,000 in FY2026E from the $228,140 FY2025A actual (a -34.3% step), then compounds at the scenario rate below. H1 FY2026 actual was $65,396, cut for 'lower travel and trade show attendance costs' (MDQ2); the forecast assumes management re-spends on the international strategy it is relying on
B107: Non-comp selling expense, growth per year thereafter | G107: 0.14 | Q107: FC s4: 14%/yr -- a bull case that lands a second large international account on bear-case selling dollars would be internally inconsistent
B108: Non-comp G&A growth | G108: 0.03 | H108: 0.03 | I108: 0.03 | J108: 0.03 | K108: 0.03
B110: SCENARIO: Bear - no cost response | Q110: FC s4/s5 Bear: legacy account lost outright in FY2028E, NO cost response (CM 4.4 revealed preference)
...

Sheet Owners Earnings
B1: NamSys Inc. -- historical and forecast OWNERS' EARNINGS
B2: Columns C:F are reported actuals normalised per owners_earnings_and_roic.md; columns G:K are the driver-based forecast per forecast_earnings.md, shown side by side on the identical bridge. Column M is the TTM memo. The forecast scenario displayed is switched at Inputs!C17.
B4: A. OWNERS' EARNINGS BRIDGE -- HISTORICAL (C:F) AND FORECAST (G:K) SIDE BY SIDE
B5: Owners' earnings = reported operating income, normalised for bad debt and share-based compensation, plus depreciation less maintenance capex, taxed at 26.5% with non-deductible SBC grossed up. Interest income and FX are excluded (OE s2).
C6: FY2022A | D6: FY2023A | E6: FY2024A | F6: FY2025A | G6: FY2026E | H6: FY2027E | I6: FY2028E | J6: FY2029E | K6: FY2030E | M6: TTM Apr-26
B7: Revenue | C7: =Inputs!C35 | D7: =Inputs!D35 | E7: =Inputs!E35 | F7: =Inputs!F35 | G7: =CHOOSE(Inputs!$C$17,G53,G92,G131,G170) | H7: =CHOOSE(Inputs!$C$17,H53,H92,H131,H170) | I7: =CHOOSE(Inputs!$C$17,I53,I92,I131,I170) | J7: =CHOOSE(Inputs!$C$17,J53,J92,J131,J170) | K7: =CHOOSE(Inputs!$C$17,K53,K92,K131,K170) | M7: =Inputs!O35
B8: Revenue growth | D8: =D7/C7-1 | E8: =E7/D7-1 | F8: =F7/E7-1 | G8: =G7/F7-1 | H8: =H7/G7-1 | I8: =I7/H7-1 | J8: =J7/I7-1 | K8: =K7/J7-1
B9: Operating income | C9: =Inputs!C36 | D9: =Inputs!D36 | E9: =Inputs!E36 | F9: =Inputs!F36 | G9: =CHOOSE(Inputs!$C$17,G71,G110,G149,G188) | H9: =CHOOSE(Inputs!$C$17,H71,H110,H149,H188) | I9: =CHOOSE(Inputs!$C$17,I71,I110,I149,I188) | J9: =CHOOSE(Inputs!$C$17,J71,J110,J149,J188) | K9: =CHOOSE(Inputs!$C$17,K71,K110,K149,K188) | M9: =Inputs!O36 | Q9: Actuals: as reported (FS23/FS25/FSQ2). Forecast: built bottom-up in section B below on a NORMALISED cost base
B10: Operating margin | C10: =C9/C7 | D10: =D9/D7 | E10: =E9/E7 | F10: =F9/F7 | G10: =G9/G7 | H10: =H9/H7 | I10: =I9/I7 | J10: =J9/J7 | K10: =K9/K7 | M10: =M9/M7
B12: Adjustments to reach owners' earnings (OE s2.1):
B13: + Reported bad debt expense | C13: =Inputs!C37 | D13: =Inputs!D37 | E13: =Inputs!E37 | F13: =Inputs!F37 | G13: 0 | H13: 0 | I13: 0 | J13: 0 | K13: 0 | M13: =Inputs!O37
B14: - Normalised bad debt expense | C14: =-Inputs!$C$28 | D14: =-Inputs!$C$28 | E14: =-Inputs!$C$28 | F14: =-Inputs!$C$28 | G14: 0 | H14: 0 | I14: 0 | J14: 0 | K14: 0 | M14: =-Inputs!$C$28 | Q14: Zero in the forecast columns by construction: the forecast cost build in section B already charges NORMALISED bad debt and NORMALISED SBC, so there is nothing left to normalise
B15: + Reported share-based compensation | C15: =Inputs!C38 | D15: =Inputs!D38 | E15: =Inputs!E38 | F15: =Inputs!F38 | G15: 0 | H15: 0 | I15: 0 | J15: 0 | K15: 0 | M15: =Inputs!O38
B16: - Normalised share-based compensation | C16: =-Inputs!$C$29 | D16: =-Inputs!$C$29 | E16: =-Inputs!$C$29 | F16: =-Inputs!$C$29 | G16: 0 | H16: 0 | I16: 0 | J16: 0 | K16: 0 | M16: =-Inputs!$C$29
B17: + Depreciation of property and equipment | C17: =Inputs!C39 | D17: =Inputs!D39 | E17: =Inputs!E39 | F17: =Inputs!F39 | G17: =Inputs!$F$39 | H17: =Inputs!$F$39 | I17: =Inputs!$F$39 | J17: =Inputs!$F$39 | K17: =Inputs!$F$39 | M17: =Inputs!O39
B18: - Maintenance capex (actual purchases of PP&E) | C18: =-Inputs!C40 | D18: =-Inputs!D40 | E18: =-Inputs!E40 | F18: =-Inputs!F40 | G18: =-Inputs!$F$40 | H18: =-Inputs!$F$40 | I18: =-Inputs!$F$40 | J18: =-Inputs!$F$40 | K18: =-Inputs!$F$40 | M18: =-Inputs!O40
B19: = Normalised pre-tax owners' earnings | C19: =C9+SUM(C13:C18) | D19: =D9+SUM(D13:D18) | E19: =E9+SUM(E13:E18) | F19: =F9+SUM(F13:F18) | G19: =G9+SUM(G13:G18) | H19: =H9+SUM(H13:H18) | I19: =I9+SUM(I13:I18) | J19: =J9+SUM(J13:J18) | K19: =K9+SUM(K13:K18) | M19: =M9+SUM(M13:M18)
B20: - Normalised tax at the statutory rate on (pre-tax OE + normalised SBC) | C20: =-Inputs!$C$27*(C19+Inputs!$C$29) | D20: =-Inputs!$C$27*(D19+Inputs!$C$29) | E20: =-Inputs!$C$27*(E19+Inputs!$C$29) | F20: =-Inputs!$C$27*(F19+Inputs!$C$29) | G20: =-Inputs!$C$27*(G19+Inputs!$C$29) | H20: =-Inputs!$C$27*(H19+Inputs!$C$29) | I20: =-Inputs!$C$27*(I19+Inputs!$C$29) | J20: =-Inputs!$C$27*(J19+Inputs!$C$29) | K20: =-Inputs!$C$27*(K19+Inputs!$C$29) | M20: =-Inputs!$C$27*(M19+Inputs!$C$29) | Q20: Stock-option SBC is not deductible in Canada, so the taxable base is grossed up by normalised SBC (OE s2.2)
B21: - Other permanent tax differences | C21: =-(Inputs!C41-Inputs!C38*Inputs!$C$27) | D21: =-(Inputs!D41-Inputs!D38*Inputs!$C$27) | E21: =-(Inputs!E41-Inputs!E38*Inputs!$C$27) | F21: =-(Inputs!F41-Inputs!F38*Inputs!$C$27) | G21: =-Inputs!$C$30 | H21: =-Inputs!$C$30 | I21: =-Inputs!$C$30 | J21: =-Inputs!$C$30 | K21: =-Inputs!$C$30 | M21: =-(Inputs!O41-Inputs!O38*Inputs!$C$27) | Q21: Actuals: Note 9 'adjustments to determine taxable income' less the part explained by non-deductible SBC. Forecast: held at the Inputs constant
B22: = OWNERS' EARNINGS | C22: =C19+C20+C21 | D22: =D19+D20+D21 | E22: =E19+E20+E21 | F22: =F19+F20+F21 | G22: =G19+G20+G21 | H22: =H19+H20+H21 | I22: =I19+I20+I21 | J22: =J19+J20+J21 | K22: =K19+K20+K21 | M22: =M19+M20+M21
B23: Owners' earnings margin | C23: =C22/C7 | D23: =D22/D7 | E23: =E22/E7 | F23: =F22/F7 | G23: =G22/G7 | H23: =H22/H7 | I23: =I22/I7 | J23: =J22/J7 | K23: =K22/K7 | M23: =M22/M7
B24: Owners' earnings growth | D24: =D22/C22-1 | E24: =E22/D22-1 | F24: =F22/E22-1 | G24: =G22/F22-1 | H24: =H22/G22-1 | I24: =I22/H22-1 | J24: =J22/I22-1 | K24: =K22/J22-1
B26: Memo -- items deliberately outside owners' earnings:
B27: Reported net income | C27: =Inputs!C42 | D27: =Inputs!D42 | E27: =Inputs!E42 | F27: =Inputs!F42 | M27: =Inputs!O42
B28: Interest income (excluded; the portfolio is added separately in the valuation) | C28: =Inputs!C43 | D28: =Inputs!D43 | E28: =Inputs!E43 | F28: =Inputs!F43 | M28: =Inputs!O43
B29: FX gain / (loss) (normalised to nil) | C29: =Inputs!C44 | D29: =Inputs!D44 | E29: =Inputs!E44 | F29: =Inputs!F44 | M29: =Inputs!O44
B30: Cash flow from operating activities | C30: =Inputs!C45 | D30: =Inputs!D45 | E30: =Inputs!E45 | F30: =Inputs!F45 | M30: =Inputs!O45
B31: Cash conversion: (OCF - capex - after-tax interest) / owners' earnings | C31: =(C30-Inputs!C40-C28*(1-Inputs!$C$27))/C22 | D31: =(D30-Inputs!D40-D28*(1-Inputs!$C$27))/D22 | E31: =(E30-Inputs!E40-E28*(1-Inputs!$C$27))/E22 | F31: =(F30-Inputs!F40-F28*(1-Inputs!$C$27))/F22 | M31: =(M30-Inputs!O40-M28*(1-Inputs!$C$27))/M22 | Q31: OE s2 cash-flow sanity check: owners' earnings do show up as cash
B32: Sanity check: implied H2 FY2026 revenue vs reported H1 FY2026 | G32: =(G7-Inputs!N35)/Inputs!N35-1 | Q32: FC s6: the FY2026E forecast needs only ~2.8% sequential half-on-half revenue growth, of which ~1.2pp is the Q3 FY2026 translation tailwind (Knowledge Store ID 11). H1 FY2026 actual revenue is an input on the Inputs sheet
B34: CHECK: bridge owners' earnings less scenario-engine owners' earnings | F34: =F22-F73 | G34: =G22-CHOOSE(Inputs!$C$17,G73,G112,G151,G190) | H34: =H22-CHOOSE(Inputs!$C$17,H73,H112,H151,H190) | I34: =I22-CHOOSE(Inputs!$C$17,I73,I112,I151,I190) | J34: =J22-CHOOSE(Inputs!$C$17,J73,J112,J151,J190) | K34: =K22-CHOOSE(Inputs!$C$17,K73,K112,K151,K190) | Q34: must be zero in every column -- the two halves of the sheet are the same calculation
B37: SCENARIO ENGINE -- BASE (FC s4/s5 Base: legacy US account -20%/yr, Mexico rollout decelerates, headcount to 26 by FY2030E)
F38: FY2025A | G38: FY2026E | H38: FY2027E | I38: FY2028E | J38: FY2029E | K38: FY2030E
B39: Revenue drivers (linked to Inputs section 7)
B40: US ex-legacy growth (constant currency, USD) | G40: =Inputs!G82 | H40: =Inputs!H82 | I40: =Inputs!I82 | J40: =Inputs!J82 | K40: =Inputs!K82
B41: Legacy largest US account growth (USD) | G41: =Inputs!G83 | H41: =Inputs!H83 | I41: =Inputs!I83 | J41: =Inputs!J83 | K41: =Inputs!K83
B42: Mexico account growth (USD) | G42: =Inputs!G84 | H42: =Inputs!H84 | I42: =Inputs!I84 | J42: =Inputs!J84 | K42: =Inputs!K84
B43: Other international growth (USD) | G43: =Inputs!G85 | H43: =Inputs!H85 | I43: =Inputs!I85 | J43: =Inputs!J85 | K43: =Inputs!K85
B44: Canada growth (CAD) | G44: =Inputs!G86 | H44: =Inputs!H86 | I44: =Inputs!I86 | J44: =Inputs!J86 | K44: =Inputs!K86
B45: US base excluding legacy account (USD) | F45: =Inputs!$C$58 | G45: =F45*(1+G40) | H45: =G45*(1+H40) | I45: =H45*(1+I40) | J45: =I45*(1+J40) | K45: =J45*(1+K40)
B46: Legacy largest US account (USD) | F46: =Inputs!$C$59 | G46: =F46*(1+G41) | H46: =G46*(1+H41) | I46: =H46*(1+I41) | J46: =I46*(1+J41) | K46: =J46*(1+K41)
B47: Mexico account (USD) | F47: =Inputs!$C$60 | G47: =F47*(1+G42) | H47: =G47*(1+H42) | I47: =H47*(1+I42) | J47: =I47*(1+J42) | K47: =J47*(1+K42)
B48: Other international (USD) | F48: =Inputs!$C$61 | G48: =F48*(1+G43) | H48: =G48*(1+H43) | I48: =H48*(1+I43) | J48: =I48*(1+J43) | K48: =J48*(1+K43)
B49: = Total USD-billed revenue (USD) | F49: =SUM(F45:F48) | G49: =SUM(G45:G48) | H49: =SUM(H45:H48) | I49: =SUM(I45:I48) | J49: =SUM(J45:J48) | K49: =SUM(K45:K48)
B50: USD/CAD average rate | F50: =Inputs!$C$55 | G50: =Inputs!G87 | H50: =Inputs!H87 | I50: =Inputs!I87 | J50: =Inputs!J87 | K50: =Inputs!K87
B51: USD-billed revenue translated to CAD | F51: =F49*F50 | G51: =G49*G50 | H51: =H49*H50 | I51: =I49*I50 | J51: =J49*J50 | K51: =K49*K50
B52: Canada revenue (CAD, not translated) | F52: =Inputs!$C$62 | G52: =F52*(1+G44) | H52: =G52*(1+H44) | I52: =H52*(1+I44) | J52: =I52*(1+J44) | K52: =J52*(1+K44)
B53: = TOTAL REVENUE (CAD) | F53: =F51+F52 | G53: =G51+G52 | H53: =H51+H52 | I53: =I51+I52 | J53: =J51+J52 | K53: =K51+K52
B54: Revenue growth | F54: =F53/Inputs!E35-1 | G54: =G53/F53-1 | H54: =H53/G53-1 | I54: =I53/H53-1 | J54: =J53/I53-1 | K54: =K53/J53-1
B56: Cost build
B57: Average headcount | F57: =Inputs!$C$71 | G57: =Inputs!G88 | H57: =Inputs!H88 | I57: =Inputs!I88 | J57: =Inputs!J88 | K57: =Inputs!K88
B58: Wage inflation | G58: =Inputs!G89 | H58: =Inputs!H89 | I58: =Inputs!I89 | J58: =Inputs!J89 | K58: =Inputs!K89
B59: Cumulative wage index vs FY2025 | F59: =1 | G59: =F59*(1+G58) | H59: =G59*(1+H58) | I59: =H59*(1+I58) | J59: =I59*(1+J58) | K59: =J59*(1+K58)
B60: Cash compensation per head | F60: =Inputs!$C$73 | G60: =$F$60*G59 | H60: =$F$60*H59 | I60: =$F$60*I59 | J60: =$F$60*J59 | K60: =$F$60*K59
B61: Cash compensation (= headcount x cost per head) | F61: =F57*F60 | G61: =G57*G60 | H61: =H57*H60 | I61: =I57*I60 | J61: =J57*J60 | K61: =K57*K60
B62: Normalised share-based compensation | F62: =Inputs!$C$29 | G62: =Inputs!$C$29 | H62: =Inputs!$C$29 | I62: =Inputs!$C$29 | J62: =Inputs!$C$29 | K62: =Inputs!$C$29
B63: Non-comp cost-of-sales elasticity to revenue growth | G63: =Inputs!G90 | H63: =Inputs!H90 | I63: =Inputs!I90 | J63: =Inputs!J90 | K63: =Inputs!K90
B64: Non-compensation cost of sales | F64: =Inputs!$C$74 | G64: =F64*(1+G63*(G53/F53-1)) | H64: =G64*(1+H63*(H53/G53-1)) | I64: =H64*(1+I63*(I53/H53-1)) | J64: =I64*(1+J63*(J53/I53-1)) | K64: =J64*(1+K63*(K53/J53-1))
B65: Non-comp G&A growth | G65: =Inputs!G93 | H65: =Inputs!H93 | I65: =Inputs!I93 | J65: =Inputs!J93 | K65: =Inputs!K93
B66: Non-compensation general and administration | F66: =Inputs!$C$76 | G66: =F66*(1+G65) | H66: =G66*(1+H65) | I66: =H66*(1+I65) | J66: =I66*(1+J65) | K66: =J66*(1+K65)
B67: Non-compensation selling expense | F67: =Inputs!$C$75 | G67: =Inputs!$G$91 | H67: =G67*(1+Inputs!$G$92) | I67: =H67*(1+Inputs!$G$92) | J67: =I67*(1+Inputs!$G$92) | K67: =J67*(1+Inputs!$G$92)
B68: Memo: implied growth in non-comp selling | G68: =G67/F67-1 | H68: =H67/G67-1 | I68: =I67/H67-1 | J68: =J67/I67-1 | K68: =K67/J67-1 | Q68: FY2026E shows the -34.3% reset from the $228,140 FY2025A actual; FY2027E-FY2030E show the scenario growth rate, confirming the two Inputs-sheet parameters drive all five years
B69: Normalised bad debt expense | F69: =Inputs!$C$28 | G69: =Inputs!$C$28 | H69: =Inputs!$C$28 | I69: =Inputs!$C$28 | J69: =Inputs!$C$28 | K69: =Inputs!$C$28
B70: = Total operating cost | F70: =F61+F62+F64+F66+F67+F69 | G70: =G61+G62+G64+G66+G67+G69 | H70: =H61+H62+H64+H66+H67+H69 | I70: =I61+I62+I64+I66+I67+I69 | J70: =J61+J62+J64+J66+J67+J69 | K70: =K61+K62+K64+K66+K67+K69
B71: = OPERATING INCOME (normalised cost base) | F71: =F53-F70 | G71: =G53-G70 | H71: =H53-H70 | I71: =I53-I70 | J71: =J53-J70 | K71: =K53-K70
B72: Operating margin | F72: =F71/F53 | G72: =G71/G53 | H72: =H71/H53 | I72: =I71/I53 | J72: =J71/J53 | K72: =K71/K53
B73: = OWNERS' EARNINGS (see bridge above; repeated here) | F73: =(F71+Inputs!$F$39-Inputs!$F$40)*(1-Inputs!$C$27)-Inputs!$C$27*Inputs!$C$29-(Inputs!$F$41-Inputs!$F$38*Inputs!$C$27) | G73: =(G71+Inputs!$F$39-Inputs!$F$40)*(1-Inputs!$C$27)-Inputs!$C$27*Inputs!$C$29-Inputs!$C$30 | H73: =(H71+Inputs!$F$39-Inputs!$F$40)*(1-Inputs!$C$27)-Inputs!$C$27*Inputs!$C$29-Inputs!$C$30 | I73: =(I71+Inputs!$F$39-Inputs!$F$40)*(1-Inputs!$C$27)-Inputs!$C$27*Inputs!$C$29-Inputs!$C$30 | J73: =(J71+Inputs!$F$39-Inputs!$F$40)*(1-Inputs!$C$27)-Inputs!$C$27*Inputs!$C$29-Inputs!$C$30 | K73: =(K71+Inputs!$F$39-Inputs!$F$40)*(1-Inputs!$C$27)-Inputs!$C$27*Inputs!$C$29-Inputs!$C$30 | Q73: Algebraically identical to the bridge above: (pre-tax OE) - [tax x (pre-tax OE + normalised SBC)] - permanent differences
B74: Owners' earnings margin | F74: =F73/F53 | G74: =G73/G53 | H74: =H73/H53 | I74: =I73/I53 | J74: =J73/J53 | K74: =K73/K53
B76: SCENARIO ENGINE -- BULL (FC s4/s5 Bull: legacy stabilises, a 2nd Mexico-sized international account lands from FY2028E)
F77: FY2025A | G77: FY2026E | H77: FY2027E | I77: FY2028E | J77: FY2029E | K77: FY2030E
B78: Revenue drivers (linked to Inputs section 7)
B79: US ex-legacy growth (constant currency, USD) | G79: =Inputs!G97 | H79: =Inputs!H97 | I79: =Inputs!I97 | J79: =Inputs!J97 | K79: =Inputs!K97
B80: Legacy largest US account growth (USD) | G80: =Inputs!G98 | H80: =Inputs!H98 | I80: =Inputs!I98 | J80: =Inputs!J98 | K80: =Inputs!K98
B81: Mexico account growth (USD) | G81: =Inputs!G99 | H81: =Inputs!H99 | I81: =Inputs!I99 | J81: =Inputs!J99 | K81: =Inputs!K99
B82: Other international growth (USD) | G82: =Inputs!G100 | H82: =Inputs!H100 | I82: =Inputs!I100 | J82: =Inputs!J100 | K82: =Inputs!K100
B83: Canada growth (CAD) | G83: =Inputs!G101 | H83: =Inputs!H101 | I83: =Inputs!I101 | J83: =Inputs!J101 | K83: =Inputs!K101
B84: US base excluding legacy account (USD) | F84: =Inputs!$C$58 | G84: =F84*(1+G79) | H84: =G84*(1+H79) | I84: =H84*(1+I79) | J84: =I84*(1+J79) | K84: =J84*(1+K79)
B85: Legacy largest US account (USD) | F85: =Inputs!$C$59 | G85: =F85*(1+G80) | H85: =G85*(1+H80) | I85: =H85*(1+I80) | J85: =I85*(1+J80) | K85: =J85*(1+K80)
B86: Mexico account (USD) | F86: =Inputs!$C$60 | G86: =F86*(1+G81) | H86: =G86*(1+H81) | I86: =H86*(1+I81) | J86: =I86*(1+J81) | K86: =J86*(1+K81)
B87: Other international (USD) | F87: =Inputs!$C$61 | G87: =F87*(1+G82) | H87: =G87*(1+H82) | I87: =H87*(1+I82) | J87: =I87*(1+J82) | K87: =J87*(1+K82)
B88: = Total USD-billed revenue (USD) | F88: =SUM(F84:F87) | G88: =SUM(G84:G87) | H88: =SUM(H84:H87) | I88: =SUM(I84:I87) | J88: =SUM(J84:J87) | K88: =SUM(K84:K87)
B89: USD/CAD average rate | F89: =Inputs!$C$55 | G89: =Inputs!G102 | H89: =Inputs!H102 | I89: =Inputs!I102 | J89: =Inputs!J102 | K89: =Inputs!K102
B90: USD-billed revenue translated to CAD | F90: =F88*F89 | G90: =G88*G89 | H90: =H88*H89 | I90: =I88*I89 | J90: =J88*J89 | K90: =K88*K89
B91: Canada revenue (CAD, not translated) | F91: =Inputs!$C$62 | G91: =F91*(1+G83) | H91: =G91*(1+H83) | I91: =H91*(1+I83) | J91: =I91*(1+J83) | K91: =J91*(1+K83)
B92: = TOTAL REVENUE (CAD) | F92: =F90+F91 | G92: =G90+G91 | H92: =H90+H91 | I92: =I90+I91 | J92: =J90+J91 | K92: =K90+K91
B93: Revenue growth | F93: =F92/Inputs!E35-1 | G93: =G92/F92-1 | H93: =H92/G92-1 | I93: =I92/H92-1 | J93: =J92/I92-1 | K93: =K92/J92-1
B95: Cost build
B96: Average headcount | F96: =Inputs!$C$71 | G96: =Inputs!G103 | H96: =Inputs!H103 | I96: =Inputs!I103 | J96: =Inputs!J103 | K96: =Inputs!K103
B97: Wage inflation | G97: =Inputs!G104 | H97: =Inputs!H104 | I97: =Inputs!I104 | J97: =Inputs!J104 | K97: =Inputs!K104
B98: Cumulative wage index vs FY2025 | F98: =1 | G98: =F98*(1+G97) | H98: =G98*(1+H97) | I98: =H98*(1+I97) | J98: =I98*(1+J97) | K98: =J98*(1+K97)
B99: Cash compensation per head | F99: =Inputs!$C$73 | G99: =$F$99*G98 | H99: =$F$99*H98 | I99: =$F$99*I98 | J99: =$F$99*J98 | K99: =$F$99*K98
B100: Cash compensation (= headcount x cost per head) | F100: =F96*F99 | G100: =G96*G99 | H100: =H96*H99 | I100: =I96*I99 | J100: =J96*J99 | K100: =K96*K99
B101: Normalised share-based compensation | F101: =Inputs!$C$29 | G101: =Inputs!$C$29 | H101: =Inputs!$C$29 | I101: =Inputs!$C$29 | J101: =Inputs!$C$29 | K101: =Inputs!$C$29
B102: Non-comp cost-of-sales elasticity to revenue growth | G102: =Inputs!G105 | H102: =Inputs!H105 | I102: =Inputs!I105 | J102: =Inputs!J105 | K102: =Inputs!K105
B103: Non-compensation cost of sales | F103: =Inputs!$C$74 | G103: =F103*(1+G102*(G92/F92-1)) | H103: =G103*(1+H102*(H92/G92-1)) | I103: =H103*(1+I102*(I92/H92-1)) | J103: =I103*(1+J102*(J92/I92-1)) | K103: =J103*(1+K102*(K92/J92-1))
B104: Non-comp G&A growth | G104: =Inputs!G108 | H104: =Inputs!H108 | I104: =Inputs!I108 | J104: =Inputs!J108 | K104: =Inputs!K108
B105: Non-compensation general and administration | F105: =Inputs!$C$76 | G105: =F105*(1+G104) | H105: =G105*(1+H104) | I105: =H105*(1+I104) | J105: =I105*(1+J104) | K105: =J105*(1+K104)
B106: Non-compensation selling expense | F106: =Inputs!$C$75 | G106: =Inputs!$G$106 | H106: =G106*(1+Inputs!$G$107) | I106: =H106*(1+Inputs!$G$107) | J106: =I106*(1+Inputs!$G$107) | K106: =J106*(1+Inputs!$G$107)
B107: Memo: implied growth in non-comp selling | G107: =G106/F106-1 | H107: =H106/G106-1 | I107: =I106/H106-1 | J107: =J106/I106-1 | K107: =K106/J106-1 | Q107: FY2026E shows the -34.3% reset from the $228,140 FY2025A actual; FY2027E-FY2030E show the scenario growth rate, confirming the two Inputs-sheet parameters drive all five years
B108: Normalised bad debt expense | F108: =Inputs!$C$28 | G108: =Inputs!$C$28 | H108: =Inputs!$C$28 | I108: =Inputs!$C$28 | J108: =Inputs!$C$28 | K108: =Inputs!$C$28
B109: = Total operating cost | F109: =F100+F101+F103+F105+F106+F108 | G109: =G100+G101+G103+G105+G106+G108 | H109: =H100+H101+H103+H105+H106+H108 | I109: =I100+I101+I103+I105+I106+I108 | J109: =J100+J101+J103+J105+J106+J108 | K109: =K100+K101+K103+K105+K106+K108
...

Sheet Valuation
B1: NamSys Inc. -- TERMINAL VALUE AND SUM-OF-THE-PARTS VALUATION
B2: Value per diluted share = PV of FY2026E-FY2030E owners' earnings + PV of the terminal value at October 31 2030 + standalone financial assets - debt-like items, divided by current diluted shares. Deliberately stock-price-blind: no quote or market capitalisation is used anywhere.
B4: A. TERMINAL VALUE AT OCTOBER 31, 2030 (TV s6) -- NOT yet discounted
B5: Scenario | C5: FY2030E owners' earnings | D5: Terminal multiple | E5: Terminal value at 31-Oct-2030
B6: Bull | C6: ='Owners Earnings'!K112 | D6: =Inputs!$C$24 | E6: =C6*D6
B7: Base | C7: ='Owners Earnings'!K73 | D7: =Inputs!$C$21 | E7: =C7*D7 | Q7: TV s6: 12x is the base multiple; the scenario-consistent 'diagonal' pairs 15x with bull and 8x with both bear variants, because the multiple and the earnings path are not independent (TV s1)
B8: Bear - management right-sizes | C8: ='Owners Earnings'!K190 | D8: =Inputs!$C$23 | E8: =C8*D8
B9: Bear - no cost response | C9: ='Owners Earnings'!K151 | D9: =Inputs!$C$23 | E9: =C9*D9
B11: Base-case terminal value across the defensible multiple range (TV s5):
B12: Low end of range | C12: =C7 | D12: =Inputs!$C$20 | E12: =C12*D12
B13: Base | C13: =C7 | D13: =Inputs!$C$21 | E13: =C13*D13
B14: High end of range | C14: =C7 | D14: =Inputs!$C$22 | E14: =C14*D14
B16: B. DISCOUNTING CONVENTION (VAL s2)
B17: The current fiscal year (FY2026, in progress) is t=0 and is NOT discounted. The terminal value is a value AS OF the end of FY2030E, the same time point as the FY2030E cash flow, so it carries the SAME t=4 factor.
G18: FY2026E | H18: FY2027E | I18: FY2028E | J18: FY2029E | K18: FY2030E
B19: Discount period t (years from today) | G19: 0 | H19: 1 | I19: 2 | J19: 3 | K19: 4 | Q19: VAL s2 convention -- editable
B20: Discount factor = 1 / (1 + r)^t | G20: =1/(1+Inputs!$C$7)^G19 | H20: =1/(1+Inputs!$C$7)^H19 | I20: =1/(1+Inputs!$C$7)^I19 | J20: =1/(1+Inputs!$C$7)^J19 | K20: =1/(1+Inputs!$C$7)^K19
B21: Terminal-value discount factor (t = 4, same as FY2030E) | C21: =K20
B23: C. PRESENT VALUE OF FY2026E-FY2030E OWNERS' EARNINGS, BY SCENARIO
B24: The April 30, 2026 balance already contains the operating cash NamSys generated in H1 FY2026. That amount is netted out of the undiscounted t=0 flow so it is counted exactly once (VAL s3.1). It is a realised historical figure, so it is identical in every scenario.
B25: Bull: | E25: PV, sum
B26: Owners' earnings as forecast | G26: ='Owners Earnings'!G112 | H26: ='Owners Earnings'!H112 | I26: ='Owners Earnings'!I112 | J26: ='Owners Earnings'!J112 | K26: ='Owners Earnings'!K112
B27: less H1 FY2026 operating cash already inside the Apr-30-26 balance | G27: =-Inputs!$N$45 | Q27: FSQ2 statements of cash flows, six months ended Apr 30 2026 = 1,497,265 (VAL s3.1)
B28: = Flow discounted at t | G28: =G26+IF(G19=0,G27,0) | H28: =H26 | I28: =I26 | J28: =J26 | K28: =K26
B29: PV of flow | E29: =SUM(G29:K29) | G29: =G28*G20 | H29: =H28*H20 | I29: =I28*I20 | J29: =J28*J20 | K29: =K28*K20
B31: Base: | E31: PV, sum
B32: Owners' earnings as forecast | G32: ='Owners Earnings'!G73 | H32: ='Owners Earnings'!H73 | I32: ='Owners Earnings'!I73 | J32: ='Owners Earnings'!J73 | K32: ='Owners Earnings'!K73
B33: less H1 FY2026 operating cash already inside the Apr-30-26 balance | G33: =-Inputs!$N$45 | Q33: FSQ2 statements of cash flows, six months ended Apr 30 2026 = 1,497,265 (VAL s3.1)
B34: = Flow discounted at t | G34: =G32+IF(G19=0,G33,0) | H34: =H32 | I34: =I32 | J34: =J32 | K34: =K32
B35: PV of flow | E35: =SUM(G35:K35) | G35: =G34*G20 | H35: =H34*H20 | I35: =I34*I20 | J35: =J34*J20 | K35: =K34*K20
B37: Bear - management right-sizes: | E37: PV, sum
B38: Owners' earnings as forecast | G38: ='Owners Earnings'!G190 | H38: ='Owners Earnings'!H190 | I38: ='Owners Earnings'!I190 | J38: ='Owners Earnings'!J190 | K38: ='Owners Earnings'!K190
B39: less H1 FY2026 operating cash already inside the Apr-30-26 balance | G39: =-Inputs!$N$45 | Q39: FSQ2 statements of cash flows, six months ended Apr 30 2026 = 1,497,265 (VAL s3.1)
B40: = Flow discounted at t | G40: =G38+IF(G19=0,G39,0) | H40: =H38 | I40: =I38 | J40: =J38 | K40: =K38
B41: PV of flow | E41: =SUM(G41:K41) | G41: =G40*G20 | H41: =H40*H20 | I41: =I40*I20 | J41: =J40*J20 | K41: =K40*K20
B43: Bear - no cost response: | E43: PV, sum
B44: Owners' earnings as forecast | G44: ='Owners Earnings'!G151 | H44: ='Owners Earnings'!H151 | I44: ='Owners Earnings'!I151 | J44: ='Owners Earnings'!J151 | K44: ='Owners Earnings'!K151
B45: less H1 FY2026 operating cash already inside the Apr-30-26 balance | G45: =-Inputs!$N$45 | Q45: FSQ2 statements of cash flows, six months ended Apr 30 2026 = 1,497,265 (VAL s3.1)
B46: = Flow discounted at t | G46: =G44+IF(G19=0,G45,0) | H46: =H44 | I46: =I44 | J46: =J44 | K46: =K44
B47: PV of flow | E47: =SUM(G47:K47) | G47: =G46*G20 | H47: =H46*H20 | I47: =I46*I20 | J47: =J46*J20 | K47: =K46*K20
B49: D. SUM OF THE PARTS -- BASE CASE (VAL s4)
B50: PV of FY2026E-FY2030E owners' earnings | C50: =E35
B51: + PV of terminal value (base multiple x FY2030E OE, discounted at t=4) | C51: =E7*C21
B52: = PV of the operating business | C52: =SUM(C50:C51)
B53: + Standalone assets: cash + short-term investments at Apr 30, 2026 | C53: =Inputs!$C$15 | Q53: OE s4: genuinely surplus to operations, earns 2.00-2.45%, and owners' earnings deliberately exclude the interest it generates -- so it is added at face value, not capitalised at a multiple
B54: - Debt and debt-like deductions | C54: =-Inputs!$C$16 | Q54: OE s2: no debt of any kind. The $1.1M contingent employee termination commitment is excluded unless the Inputs switch is set to 1
B55: = EQUITY VALUE | C55: =C52+C53+C54
B56: / Diluted shares outstanding | C56: =Inputs!$C$8
B57: = VALUE PER DILUTED SHARE | C57: =C55/C56
B59: E. SCENARIO SUMMARY
B60: Scenario (each with its own scenario-consistent terminal multiple) | C60: PV of 5 years of OE | D60: PV of terminal value | E60: + standalone assets | F60: - debt-like | G60: = equity value | H60: per diluted share
B61: Bull | C61: =E29 | D61: =E6*C21 | E61: =Inputs!$C$15 | F61: =-Inputs!$C$16 | G61: =SUM(C61:F61) | H61: =G61/Inputs!$C$8
B62: Base | C62: =E35 | D62: =E7*C21 | E62: =Inputs!$C$15 | F62: =-Inputs!$C$16 | G62: =SUM(C62:F62) | H62: =G62/Inputs!$C$8
B63: Bear - management right-sizes | C63: =E41 | D63: =E8*C21 | E63: =Inputs!$C$15 | F63: =-Inputs!$C$16 | G63: =SUM(C63:F63) | H63: =G63/Inputs!$C$8
B64: Bear - no cost response | C64: =E47 | D64: =E9*C21 | E64: =Inputs!$C$15 | F64: =-Inputs!$C$16 | G64: =SUM(C64:F64) | H64: =G64/Inputs!$C$8
B66: F. COMPOSITION OF THE BASE-CASE VALUE PER SHARE
C67: $ per share | D67: % of total
B68: PV of FY2026E-FY2030E owners' earnings | C68: =(C50)/Inputs!$C$8 | D68: =C68/$C$71
B69: PV of terminal value | C69: =(C51)/Inputs!$C$8 | D69: =C69/$C$71 | Q69: Roughly 60% of the answer is the terminal-multiple judgement call, not the five explicit forecast years (VAL s4)
B70: Standalone cash and short-term investments | C70: =(C53+C54)/Inputs!$C$8 | D70: =C70/$C$71
B71: = Total value per diluted share | C71: =SUM(C68:C70)
B73: G. BASE-CASE SENSITIVITY: VALUE PER DILUTED SHARE BY DISCOUNT RATE AND TERMINAL MULTIPLE
B74: Recomputed live from the base-case flow row in section C; the discount rate and multiple below OVERRIDE the Inputs values for this grid only.
B75: r \ terminal multiple | C75: =Inputs!$C$20 | D75: =Inputs!$C$21 | E75: =Inputs!$C$22
B76: 0.08 | C76: =(SUMPRODUCT($G$34:$K$34,1/(1+$B76)^$G$19:$K$19)+C$75*$C$7/(1+$B76)^$K$19+Inputs!$C$15-Inputs!$C$16)/Inputs!$C$8 | D76: =(SUMPRODUCT($G$34:$K$34,1/(1+$B76)^$G$19:$K$19)+D$75*$C$7/(1+$B76)^$K$19+Inputs!$C$15-Inputs!$C$16)/Inputs!$C$8 | E76: =(SUMPRODUCT($G$34:$K$34,1/(1+$B76)^$G$19:$K$19)+E$75*$C$7/(1+$B76)^$K$19+Inputs!$C$15-Inputs!$C$16)/Inputs!$C$8
B77: 0.09 | C77: =(SUMPRODUCT($G$34:$K$34,1/(1+$B77)^$G$19:$K$19)+C$75*$C$7/(1+$B77)^$K$19+Inputs!$C$15-Inputs!$C$16)/Inputs!$C$8 | D77: =(SUMPRODUCT($G$34:$K$34,1/(1+$B77)^$G$19:$K$19)+D$75*$C$7/(1+$B77)^$K$19+Inputs!$C$15-Inputs!$C$16)/Inputs!$C$8 | E77: =(SUMPRODUCT($G$34:$K$34,1/(1+$B77)^$G$19:$K$19)+E$75*$C$7/(1+$B77)^$K$19+Inputs!$C$15-Inputs!$C$16)/Inputs!$C$8
B78: 0.1 | C78: =(SUMPRODUCT($G$34:$K$34,1/(1+$B78)^$G$19:$K$19)+C$75*$C$7/(1+$B78)^$K$19+Inputs!$C$15-Inputs!$C$16)/Inputs!$C$8 | D78: =(SUMPRODUCT($G$34:$K$34,1/(1+$B78)^$G$19:$K$19)+D$75*$C$7/(1+$B78)^$K$19+Inputs!$C$15-Inputs!$C$16)/Inputs!$C$8 | E78: =(SUMPRODUCT($G$34:$K$34,1/(1+$B78)^$G$19:$K$19)+E$75*$C$7/(1+$B78)^$K$19+Inputs!$C$15-Inputs!$C$16)/Inputs!$C$8 | Q78: VAL s6: across the full defensible band the base case spans roughly $1.18-$1.76. Value is far more sensitive to the terminal multiple than to the discount rate
B79: 0.11 | C79: =(SUMPRODUCT($G$34:$K$34,1/(1+$B79)^$G$19:$K$19)+C$75*$C$7/(1+$B79)^$K$19+Inputs!$C$15-Inputs!$C$16)/Inputs!$C$8 | D79: =(SUMPRODUCT($G$34:$K$34,1/(1+$B79)^$G$19:$K$19)+D$75*$C$7/(1+$B79)^$K$19+Inputs!$C$15-Inputs!$C$16)/Inputs!$C$8 | E79: =(SUMPRODUCT($G$34:$K$34,1/(1+$B79)^$G$19:$K$19)+E$75*$C$7/(1+$B79)^$K$19+Inputs!$C$15-Inputs!$C$16)/Inputs!$C$8
B80: 0.12 | C80: =(SUMPRODUCT($G$34:$K$34,1/(1+$B80)^$G$19:$K$19)+C$75*$C$7/(1+$B80)^$K$19+Inputs!$C$15-Inputs!$C$16)/Inputs!$C$8 | D80: =(SUMPRODUCT($G$34:$K$34,1/(1+$B80)^$G$19:$K$19)+D$75*$C$7/(1+$B80)^$K$19+Inputs!$C$15-Inputs!$C$16)/Inputs!$C$8 | E80: =(SUMPRODUCT($G$34:$K$34,1/(1+$B80)^$G$19:$K$19)+E$75*$C$7/(1+$B80)^$K$19+Inputs!$C$15-Inputs!$C$16)/Inputs!$C$8
B82: H. CROSS-CHECKS AND WHAT-IFS
B83: Base-case value per share using the H1 FY2026 diluted count instead | C83: =C55/Inputs!$C$9 | Q83: VAL s6: moves the answer by ~0.14% -- the choice of share count is immaterial
B84: difference vs the headline | C84: =C83/C57-1
B85: Base-case value per share if the $1.1M termination commitment IS deducted | C85: =(C55-Inputs!$C$13*(1-Inputs!$C$14))/Inputs!$C$8 | Q85: VAL s5: costs about $0.04 per share -- flagged, not silently included
B86: Implied owners'-earnings yield on the terminal value (FY2030E OE / TV) | C86: =C7/E7 | Q86: TV s7 cross-check on the 12x multiple
B87: Implied terminal EV / FY2030E revenue | C87: =E7/'Owners Earnings'!K53 | Q87: TV s7: 3.59x sales on a ~34% operating margin, against Cerillion at 4.62x on 39.5% and Enghouse at 1.41x on 18.6%
B89: I. TIE-OUT: DOES THIS WORKBOOK REPRODUCE THE PYTHON SCRIPTS?
B90: Published equity values from work_products/valuation.md section 5 (the output of valuation_calcs.py). The residual of about -$5 on ~$40M (-0.000013%, or -$0.0000002 per share) is fully attributed in work_products/valuation_xlsx_tieout.py: -$1.00 because the workbook links normalised SBC as a live =AVERAGE() formula (352,672/3 = 117,557.33) where the script hard-coded 117,557, and -$4.29 because the workbook carries the unrounded owners'-earnings path into the terminal value where the script multiplied the rounded FY2030E figure of 2,859,320. The workbook is the more precise of the two.
C91: this workbook | D91: published | E91: difference
B92: Equity value -- Bull | C92: =G61 | D92: 67694384 | E92: =C92-D92 | Q92: work_products/valuation.md s5 (output of valuation_calcs.py)
B93: Equity value -- Base | C93: =G62 | D93: 39974178 | E93: =C93-D93 | Q93: work_products/valuation.md s5 (output of valuation_calcs.py)
B94: Equity value -- Bear - management right-sizes | C94: =G63 | D94: 25865989 | E94: =C94-D94 | Q94: work_products/valuation.md s5 (output of valuation_calcs.py)
B95: Equity value -- Bear - no cost response | C95: =G64 | D95: 21364839 | E95: =C95-D95 | Q95: work_products/valuation.md s5 (output of valuation_calcs.py)
