Workbook

Sheet 1 Earnings
A1: Boyd Group Services (BYD.TO) - Sheet 1: Owners' Earnings, historical and forecast
A2: US$ millions unless stated. Python sources: owners_earnings_roic.py (historical), forecast_earnings.py (forecast). Share price not used anywhere.
A3: Input (change me) | B3: Linked from elsewhere (do not overwrite) | F3: Black = formula
A5: INPUTS
A6: 1.1 Reported figures (US$M, from filings) | B6: FY2023 | C6: FY2024 | D6: FY2025 | E6: H1-2025 | F6: H1-2026 | L6: Source / explanation
A7: Sales | B7: 2945.988 | C7: 3070.342 | D7: 3142.794 | E7: 1558.73 | F7: 2010.328 | L7: FY2023 AFS / FY2025 AFS statements of earnings; H1 columns from Q2FY26 interim statements (owners_earnings_roic.py l.30-37)
A8: Adjusted EBITDA, Q3-2025 | B8: 98.366 | L8: Q2FY26 MD&A quarterly table, line 350
A9: Adjusted EBITDA, Q4-2025 | B9: 103.609 | L9: Q2FY26 MD&A quarterly table, line 350
A10: Adjusted EBITDA, Q1-2026 | B10: 122.385 | L10: Q2FY26 MD&A quarterly table, line 350
A11: Adjusted EBITDA, Q2-2026 | B11: 135.932 | L11: Q2FY26 MD&A quarterly table, line 350
A12: Adjusted EBITDA (company-reported) | B12: 368.247 | C12: 334.819 | D12: 376.306 | E12: =D12-B8-B9 | F12: =B10+B11 | L12: FY2023 MD&A l.282; FY2024 MD&A l.198; FY2025 MD&A l.209. H1-2025 = FY2025 less Q3 and Q4; H1-2026 = Q1 + Q2
A13: Lease principal repaid - property | B13: 95.441 | C13: 103.888 | D13: 111.142 | E13: 54.892 | F13: 72.637 | L13: Financing section of cash flow statement (FY2025 AFS l.298; Q2FY26 FS l.167)
A14: Lease principal repaid - vehicle & equipment | B14: 3.863 | C14: 5.283 | D14: 5.594 | E14: 2.815 | F14: 2.901 | L14: FY2025 AFS l.299; Q2FY26 FS l.168
A15: Lease interest paid - property | B15: 31.328 | C15: 39.464 | D15: 44.095 | E15: 21.555 | F15: 31.872 | L15: FY2025 AFS l.301; Q2FY26 FS l.171
A16: Lease interest paid - vehicle & equipment | B16: 0.728 | C16: 1.021 | D16: 0.73 | E16: 0.462 | F16: 0.531 | L16: FY2025 AFS cash flows; Q2FY26 FS l.172. FY2025 principal + interest ties to AFS Note 17 repayments 161,561
A17: Equipment purchases & facility improvements (actual) | B17: 57.482 | C17: 77.333 | D17: 54.306 | E17: 25.765 | F17: 24.802 | L17: Investing section of cash flow statement; memo only (maintenance capex is modelled at % of sales)
A18: Software purchases and licensing (actual) | B18: 1.684 | C18: 3.124 | D18: 8.094 | E18: 3.132 | F18: 0.936 | L18: Investing section of cash flow statement
A19: Income taxes paid (cash) | B19: 27.909 | C19: 12.295 | D19: 3.669 | E19: 2.555 | F19: 3.26 | L19: Supplemental CFS line: FY2023 AFS l.297, FY2024 AFS l.300, FY2025 AFS l.318, Q2FY26 l.190
A20: Acquisition & transformational cost initiatives (actual) | B20: 4.346 | C20: 9.879 | D20: 30.488 | E20: 13.773 | F20: 31.264 | L20: Statement of earnings line (FY2023 label: 'Acquisition and transaction costs')
A21: Cash flow from operations (reported) | B21: 357.545 | C21: 313.325 | D21: 352.989 | E21: 170.593 | F21: 224.591 | L21: Statements of cash flows. Boyd reports all interest and lease principal in financing (AFS Note 2u)
A22: Changes in non-cash working capital (in CFO) | B22: 19.072 | C22: -5.909 | D22: 5.752 | E22: 18.791 | F22: -6.375 | L22: Statements of cash flows; used only in the CFO reconciliation
A23: Equity-settled share-based payment added back in CFO | B23: 0 | C23: 0.928 | D23: 4.319 | E23: 1.877 | F23: 4.689 | L23: Statements of cash flows (FY2023 not separately disclosed)
A24: Other non-cash items added back in CFO | B24: 0.444 | C24: 1.033 | D24: 2.928 | E24: 0.001 | F24: 3.425 | L24: Mainly losses on disposal, already inside Adjusted EBITDA
A25: Current income tax expense (statement of earnings) | B25: 25.872 | C25: 7.667 | D25: 5.828 | E25: 10.634 | F25: 4.201 | L25: Statement of earnings; used only in the CFO reconciliation
A27: 1.2 Owners' Earnings normalization assumptions | B27: Value | L27: Source / explanation
A28: Maintenance capex, % of sales | B28: 0.017 | L28: Mgmt guidance 1.6-1.8% of sales ex network tech & new locations, midpoint (FY2025 MD&A l.526; Q2FY26 MD&A l.102). Largest single judgment in historical OE
A29: Normalized recurring acquisition cost (US$M/yr) | B29: 5 | L29: JUDGMENT: FY2022 actual 1.7, FY2023 actual 4.3 bracket the ordinary-course level (owners_earnings_and_roic.md sec 2.5)
A30: Normalized tax rate | B30: 0.265 | L30: Combined statutory rate 26.66% (2025) / 26.53% (2024), FY2025 AFS Note 10a
A32: 1.3 Forecast inputs, common to all cases | B32: Value | F32: 2026E | G32: 2027E | H32: 2028E | I32: 2029E | J32: 2030E | K32: 2031E | L32: Source / explanation
A33: FY2025 pro-forma sales (2025 acquisitions annualized) | B33: 3235.845 | L33: FY2025 AFS l.713: revenue if 2025 acquisitions owned from Jan-1-2025. Starting legacy-Boyd sales base
A34: Project 360 savings already inside FY2025 EBITDA | B34: 40 | L34: ~$40M realized in 2025 (FY2025 MD&A l.111); stripped out of the base margin, added back as savings
A35: Cumulative cost-program savings vs 2024 base (gross) | F35: 105 | G35: 116.7 | H35: 128.3 | I35: 140 | J35: 140 | K35: 140 | L35: $40M 2025, +$65M 2026, +$35M ratably 2027-29 (Q2FY26 MD&A l.70, l.221)
A36: Revenue booked in 2025 by locations acquired in 2025 | B36: 31.508 | L36: FY2025 AFS l.713
A37: Locations acquired in 2025 (number) | B37: 43 | L37: FY2025 AFS l.663
A38: Joe Hudson's pre-deal sales (TTM Jun-25) | B38: 722 | L38: JH release l.14
A39: Joe Hudson's pre-synergy Adj. EBITDA margin (pre-rent) | B39: 0.144 | L39: JH release l.14
A40: Joe Hudson's FY2026E sales (conversion-disrupted) | B40: 700 | L40: ASSUMPTION: H1'26 $342.6M x2 plus modest H2 recovery (Q2FY26 MD&A l.72, l.291)
A41: Joe Hudson's FY2026E margin | B41: 0.13 | L41: ASSUMPTION: ~$22M lost sales x ~46% gross margin = ~1.4pp below pre-deal
A42: Operating leverage: margin change per 1pp of SSS above breakeven | B42: 0.3 | L42: CALIBRATED: mgmt 2-4% SSS -> ~+20bp/yr (FY2025 call l.281); FY2024 SSS -1.8% -> margin -1.6pp
A43: Operating leverage: breakeven SSS | B43: 0.023 | L43: CALIBRATED (as above)
A44: Operating leverage: max margin gain per year | B44: 0.003 | L44: ASSUMPTION: technician capacity limits the upside
A45: Operating leverage: max margin loss per year | B45: -0.004 | L45: ASSUMPTION: management cost response limits the downside
A46: New location: tuck-in cost per location (2026 prices) | B46: 2.8 | L46: 2025 consideration $120.8M / 43 = $2.81M (FY2025 AFS l.663); H1'26 $18.9M / 7 = $2.69M
A47: New location: tuck-in mature sales (2025 prices) | B47: =(B33-D7+B36)/B37 | L47: Formula: 2025 acquired revenue annualized / 43 locations (forecast_earnings.py NewLocationInputs)
A48: New location: start-up cost per location (2026 prices) | B48: 1.7 | L48: Pooled 2022-25 leaseholds + equipment $133.7M / 79; mgmt $1.2-1.4M (Q2FY25 call l.146)
A49: New location: start-up mature sales (2025 prices) | B49: 2.95 | L49: Avg revenue per location (network $3.10M, JH $2.80M)
A50: Ramp: share of mature earnings at age 0 / 1 / 2 / 3+ (columns B-E) | B50: 0 | C50: 0.33333333 | D50: 0.66666667 | E50: 1 | L50: Age 0 = year the capex is spent. Mgmt: locations 'reach maturity by the end of their third year' (Q2FY26 MD&A l.480)
A51: New location build / purchase cost inflation per year | B51: 0.03 | L51: ASSUMPTION
A52: Software capex, % of sales | B52: 0.002 | L52: ~0.16-0.26% of sales historically (owners_earnings_and_roic.md l.103)
A53: Normalized recurring acquisition cost (US$M/yr) | B53: =B29 | L53: Linked to 1.2
A54: Tax rate | B54: =B30 | L54: Linked to 1.2
A55: One-offs: total transformation opex budget | B55: 51.5 | L55: Q2FY26 MD&A l.223
A56: One-offs: transformation opex spent to Jun-2026 | B56: 35.6 | L56: Q2FY26 MD&A l.223
A57: One-offs: total JH integration capex budget | B57: 30 | L57: Q2FY26 MD&A l.223
A58: One-offs: JH integration capex spent to Jun-2026 | B58: 9.8 | L58: Q2FY26 MD&A l.223
A59: One-offs: share of remaining spend by year | F59: 0.6 | G59: 0.4 | H59: 0 | I59: 0 | J59: 0 | K59: 0 | L59: ASSUMPTION
A60: Net debt ex-leases at Jun-30-2026 | B60: 953.1 | L60: Q2FY26 MD&A l.361 (debt net of cash, before leases). Leverage tracking only; not used in valuation
A61: Cash interest on debt (pre-tax, per year) | B61: 60 | L61: Q2'26 run-rate x2 (Q2FY26 MD&A l.390)
A62: Dividends (per year) | B62: 13 | L62: H1'26 $6.3M x2 (Q2FY26 MD&A l.390)
A63: Share of FY2026 cash flow still to come after Jun-2026 | B63: 0.5 | L63: Only H2-2026 changes net debt after the Jun-2026 starting point
A64: Forecast probability weight - Bear | B64: 0.25 | L64: forecast_earnings.py SCENARIO_WEIGHTS (used for the weighted OE line and on sheet 2)
A65: Forecast probability weight - Base | B65: 0.5
A66: Forecast probability weight - Bull | B66: 0.25
A68: 1.4 Scenario drivers | B68: Value | F68: 2026E | G68: 2027E | H68: 2028E | I68: 2029E | J68: 2030E | K68: 2031E | L68: Source / explanation
A69: Bear
A70: Industry repairable claims volume (pp) | F70: -1 | G70: -1.5 | H70: -1.5 | I70: -1.5 | J70: -1.5 | K70: -1.5 | L70: Components of same-store sales growth (forecast_earnings.md sec 2)
A71: Average total cost of repair (pp) | F71: 1 | G71: 1.5 | H71: 2 | I71: 2 | J71: 2 | K71: 2
A72: Boyd share gain (pp) | F72: 2 | G72: 1 | H72: 1 | I72: 1 | J72: 1 | K72: 1
A73: Tuck-in acquisitions opened (number) | F73: 20 | G73: 15 | H73: 15 | I73: 15 | J73: 15 | K73: 15
A74: Start-ups opened (number) | F74: 27 | G74: 20 | H74: 20 | I74: 20 | J74: 20 | K74: 20
A75: Savings retention | B75: 0.6 | L75: Share of cost-program savings kept (rest absorbed by inflation)
A76: Maintenance capex, % of sales | B76: 0.02
A77: Existing-business rent escalator | B77: 0.03 | L77: ASSUMPTION: annual growth of existing-business cash rent
A78: New-location ROIC (mature) | B78: 0.09 | L78: Mature EBITDA after rent / location cost (pre-maintenance capex, pre-tax)
A79: Base
A80: Industry repairable claims volume (pp) | F80: -1 | G80: -1 | H80: -1 | I80: -1 | J80: -1 | K80: -1
A81: Average total cost of repair (pp) | F81: 1.2 | G81: 2 | H81: 3 | I81: 3 | J81: 3 | K81: 3
A82: Boyd share gain (pp) | F82: 2 | G82: 1.5 | H82: 1 | I82: 1 | J82: 1 | K82: 1
A83: Tuck-in acquisitions opened (number) | F83: 25 | G83: 30 | H83: 30 | I83: 30 | J83: 30 | K83: 30 | L83: Base 2027+: 8 start-ups/qtr pipeline plus a similar number of tuck-ins (unit_growth_capital_check.py)
A84: Start-ups opened (number) | F84: 27 | G84: 32 | H84: 32 | I84: 32 | J84: 32 | K84: 32
A85: Savings retention | B85: 0.8 | L85: Share of cost-program savings kept (rest absorbed by inflation)
A86: Maintenance capex, % of sales | B86: =B28 | L86: Linked to 1.2 (same management guidance midpoint)
A87: Existing-business rent escalator | B87: 0.025 | L87: ASSUMPTION: annual growth of existing-business cash rent
A88: New-location ROIC (mature) | B88: 0.13 | L88: Mature EBITDA after rent / location cost (pre-maintenance capex, pre-tax)
A89: Bull
A90: Industry repairable claims volume (pp) | F90: -1 | G90: -0.5 | H90: -0.5 | I90: -0.5 | J90: -0.5 | K90: -0.5
A91: Average total cost of repair (pp) | F91: 1.2 | G91: 3 | H91: 4 | I91: 4 | J91: 4 | K91: 4
A92: Boyd share gain (pp) | F92: 2 | G92: 2 | H92: 1.5 | I92: 1.5 | J92: 1 | K92: 1
A93: Tuck-in acquisitions opened (number) | F93: 30 | G93: 40 | H93: 40 | I93: 40 | J93: 40 | K93: 40
A94: Start-ups opened (number) | F94: 27 | G94: 36 | H94: 36 | I94: 36 | J94: 36 | K94: 36
A95: Savings retention | B95: 1 | L95: Share of cost-program savings kept (rest absorbed by inflation)
A96: Maintenance capex, % of sales | B96: 0.016
A97: Existing-business rent escalator | B97: 0.025 | L97: ASSUMPTION: annual growth of existing-business cash rent
A98: New-location ROIC (mature) | B98: 0.17 | L98: Mature EBITDA after rent / location cost (pre-maintenance capex, pre-tax)
A99: No growth (existing business only)
A100: Industry repairable claims volume (pp) | F100: =F80 | G100: =G80 | H100: =H80 | I100: =I80 | J100: =J80 | K100: =K80
A101: Average total cost of repair (pp) | F101: =F81 | G101: =G81 | H101: =H81 | I101: =I81 | J101: =J81 | K101: =K81
A102: Boyd share gain (pp) | F102: =F82 | G102: =G82 | H102: =H82 | I102: =I82 | J102: =J82 | K102: =K82
A103: Tuck-in acquisitions opened (number) | F103: 0 | G103: 0 | H103: 0 | I103: 0 | J103: 0 | K103: 0 | L103: No locations opened from 2026
A104: Start-ups opened (number) | F104: 0 | G104: 0 | H104: 0 | I104: 0 | J104: 0 | K104: 0
...

Sheet 2 Terminal Value
A1: Boyd Group Services (BYD.TO) - Sheet 2: Terminal value at end-2031 (undiscounted)
A2: US$ millions. TV = EV/EBITDA-after-rent multiple x FY2031E EBITDA after rent + same multiple x ramp gap. Python source: terminal_value.py. Multiples from collision-repair deal evidence, not Boyd's share price.
A3: Input (change me) | B3: Linked from elsewhere (do not overwrite) | F3: Black = formula
A5: INPUTS
A6: 2.1 Exit multiple (EV / EBITDA after rent) | B6: Bear | C6: Base | D6: No growth | E6: Bull | L6: Source / explanation
A7: Chosen exit multiple | B7: 6 | C7: 8.5 | D7: 8.5 | E7: 10 | L7: JUDGMENT within the deal evidence in 2.4 (terminal_value.md sec 6-7). No growth = base (same network)
A9: 2.2 Steady-state assumptions (value-driver cross-check only) | B9: Bear | C9: Base | D9: No growth | E9: Bull | L9: Source / explanation
A10: Growth without new capital (claims volume + repair cost) | B10: 0.005 | C10: 0.02 | D10: =C10 | E10: 0.025 | L10: Bear -1.5+2.0; Base -1.0+3.0; Bull capped so total g = 3% (impairment test)
A11: Growth from share gains needing new capacity | B11: 0.005 | C11: 0.005 | D11: 0 | E11: 0.005 | L11: None in the no-growth-capex case
A12: After-tax OE yield on new capacity | B12: 0.045 | C12: 0.077 | D12: =C12 | E12: 0.108 | L12: Mature unit OE yield (forecast_earnings.md sec 6.4)
A14: 2.3 Other cross-check inputs | B14: Value | L14: Source / explanation
A15: Boyd impairment test: terminal growth | B15: 0.03 | L15: FY2025 AFS l.966
A16: Boyd impairment test: WACC low | B16: 0.07 | L16: FY2025 AFS l.966
A17: Boyd impairment test: WACC high | B17: 0.09 | L17: FY2025 AFS l.966
A18: Cross-check discount rate (midpoint of impairment WACC) | B18: =AVERAGE(B16,B17) | L18: Formula. Used only for value-driver check and to compound 2026-31 cash in 3.4
A19: Management Adj. EBITDA margin target | B19: 0.14 | L19: Q2FY26 MD&A (14% target); used in the margin-normalization check
A20: Forecast weight - Bear | B20: ='1 Earnings'!B64 | L20: Linked to sheet 1
A21: Forecast weight - Base | B21: ='1 Earnings'!B65 | L21: Linked to sheet 1
A22: Forecast weight - Bull | B22: ='1 Earnings'!B66 | L22: Linked to sheet 1
A24: 2.4 Collision-repair valuation evidence (EV / EBITDA after rent) | B24: Low | C24: High | D24: Mid | L24: Source / explanation
A25: Single shops | B25: 3 | C25: 5 | D25: =AVERAGE(B25,C25) | L25: Knowledge Store IDs 11, 28
A26: Small / medium MSOs bought by consolidators | B26: 5 | C26: 7 | D26: =AVERAGE(B26,C26) | L26: Knowledge Store IDs 20, 28
A27: Market average, 2025 (weak claims year) | B27: 7 | C27: 7 | D27: =AVERAGE(B27,C27) | L27: Knowledge Store IDs 19
A28: MSOs with strong DRP relationships | B28: 7 | C28: 10 | D28: =AVERAGE(B28,C28) | L28: Knowledge Store IDs 11
A29: Platform-grade MSOs | B29: 8 | C29: 12 | D29: =AVERAGE(B29,C29) | L29: Knowledge Store IDs 11
A30: PE platform recap (illustrative) | B30: 10 | C30: 10 | D30: =AVERAGE(B30,C30) | L30: Knowledge Store IDs 21
A31: PE platforms raising capital, 2024 | B31: 12 | C31: 14 | D31: =AVERAGE(B31,C31) | L31: Knowledge Store IDs 20, 21
A32: Joe Hudson's to TSG, 2019 ('north of 13x') | B32: 13 | C32: 13 | D32: =AVERAGE(B32,C32) | L32: Knowledge Store IDs 25
A33: Joe Hudson's to Boyd, 2025, run-rate pre-synergy | B33: 13.3 | C33: 13.3 | D33: =AVERAGE(B33,C33) | L33: JH release l.43
A34: Joe Hudson's to Boyd, 2025, run-rate + synergies | B34: 9.3 | C34: 9.3 | D34: =AVERAGE(B34,C34) | L34: JH release l.43
A36: 2.5 Joe Hudson's deal (fetched_docs/boyd_joe_hudsons_acquisition_announcement.md) | B36: Value | L36: Source / explanation
A37: Purchase price | B37: 1300 | L37: line 13
A38: Expected tax benefits | B38: 150 | L38: line 43 ('approximately $150 million'); also used as a standalone asset on sheet 3
A39: JHCC Adj. EBITDA, US GAAP (after rent), TTM | B39: 63 | L39: line 37
A40: JHCC Adj. EBITDA, IFRS-like (pre-rent), TTM | B40: 104 | L40: line 37
A41: Disclosed multiple, run-rate pre-synergy | B41: 13.3 | L41: line 43
A42: Disclosed multiple, run-rate + synergies | B42: 9.3 | L42: line 43
A43: Disclosed synergies, low | B43: 35 | L43: line 45
A44: Disclosed synergies, high | B44: 45 | L44: line 45
A46: 2.6 AMA Group (ASX: AMA), listed pure-play, A$M | B46: Value | L46: Source / explanation
A47: Market capitalization (2026-09-25) | B47: 238.42 | L47: Knowledge Store ID 26 (moderate confidence)
A48: Net debt, FY26 (ex-leases) | B48: 18.4 | L48: Knowledge Store ID 26
A49: EBITDA FY26 (pre-AASB 16, i.e. after rent) | B49: 68 | L49: Knowledge Store ID 26
A50: EBITDA FY27 guidance low | B50: 75 | L50: Knowledge Store ID 26
A51: EBITDA FY27 guidance high | B51: 80 | L51: Knowledge Store ID 26
A53: 2.7 Sensitivity axes
A54: Exit multiples to test | B54: 7 | C54: 7.5 | D54: 8 | E54: 8.5 | F54: 9 | G54: 9.3 | H54: 10
A55: Discount rates to test (value-driver grid) | B55: 0.08 | C55: 0.09 | D55: 0.1
A56: Total growth rates to test (value-driver grid) | B56: 0.015 | C56: 0.02 | D56: 0.025 | E56: 0.03
A58: CALCULATIONS
A59: 2.8 FY2031E terminal-year inputs (linked from sheet 1) | B59: Bear | C59: Base | D59: No growth | E59: Bull | F59: Weighted | L59: Source / explanation
A60: FY2031E total sales | B60: ='1 Earnings'!K322 | C60: ='1 Earnings'!K416 | D60: ='1 Earnings'!K604 | E60: ='1 Earnings'!K510
A61: FY2031E EBITDA after rent | B61: ='1 Earnings'!K324 | C61: ='1 Earnings'!K418 | D61: ='1 Earnings'!K606 | E61: ='1 Earnings'!K512
A62: of which new locations | B62: ='1 Earnings'!K317 | C62: ='1 Earnings'!K411 | D62: ='1 Earnings'!K599 | E62: ='1 Earnings'!K505
A63: New-location run-rate EBITDA after rent | B63: ='1 Earnings'!K319 | C63: ='1 Earnings'!K413 | D63: ='1 Earnings'!K601 | E63: ='1 Earnings'!K507
A64: FY2031E Owners' Earnings | B64: ='1 Earnings'!K329 | C64: ='1 Earnings'!K423 | D64: ='1 Earnings'!K611 | E64: ='1 Earnings'!K517
A65: FY2031E existing-business margin | B65: ='1 Earnings'!K262 | C65: ='1 Earnings'!K356 | D65: ='1 Earnings'!K544 | E65: ='1 Earnings'!K450
A66: FY2031E existing-business sales | B66: ='1 Earnings'!K256 | C66: ='1 Earnings'!K350 | D66: ='1 Earnings'!K538 | E66: ='1 Earnings'!K444
A68: 2.9 Terminal value at end-2031 (undiscounted) | B68: Bear | C68: Base | D68: No growth | E68: Bull | F68: Weighted | L68: Source / explanation
A69: Weighted column = Bear/Base/Bull at the sheet 1 forecast weights (25/50/25); memo only. Sheet 3 applies its own case weights.
A70: Ramp gap = run-rate less actual new-location EBITDA after rent | B70: =B63-B62 | C70: =C63-C62 | D70: =D63-D62 | E70: =E63-E62 | L70: Earnings already paid for (capex spent) but not yet earned in 2031
A71: Multiple x FY2031E EBITDA after rent | B71: =B7*B61 | C71: =C7*C61 | D71: =D7*D61 | E71: =E7*E61 | F71: =$B$20*B71+$B$21*C71+$B$22*E71
A72: Plus: ramp uplift = multiple x ramp gap | B72: =B7*B70 | C72: =C7*C70 | D72: =D7*D70 | E72: =E7*E70 | F72: =$B$20*B72+$B$21*C72+$B$22*E72 | L72: No deduction for the 1-3 years before the gap is earned
A73: Terminal value, end-2031 | B73: =B71+B72 | C73: =C71+C72 | D73: =D71+D72 | E73: =E71+E72 | F73: =$B$20*B73+$B$21*C73+$B$22*E73
A74: TV / FY2031E Owners' Earnings | B74: =B73/B64 | C74: =C73/C64 | D74: =D73/D64 | E74: =E73/E64 | F74: =F73/($B$20*B64+$B$21*C64+$B$22*E64)
A75: Effective multiple on EBITDA after rent | B75: =B71/B61 | C75: =C71/C61 | D75: =D71/D61 | E75: =E71/E61 | F75: =F71/($B$20*B61+$B$21*C61+$B$22*E61)
A77: 2.10 Base and no-growth TV sensitivity to the exit multiple | B77: Multiple | C77: Base TV | D77: No growth TV | L77: Source / explanation
A78: TV at multiple | B78: =$B$54 | C78: =$B$54*($C$61+$C$70) | D78: =$B$54*($D$61+$D$70)
A79: TV at multiple | B79: =$C$54 | C79: =$C$54*($C$61+$C$70) | D79: =$C$54*($D$61+$D$70)
A80: TV at multiple | B80: =$D$54 | C80: =$D$54*($C$61+$C$70) | D80: =$D$54*($D$61+$D$70)
A81: TV at multiple | B81: =$E$54 | C81: =$E$54*($C$61+$C$70) | D81: =$E$54*($D$61+$D$70)
A82: TV at multiple | B82: =$F$54 | C82: =$F$54*($C$61+$C$70) | D82: =$F$54*($D$61+$D$70)
A83: TV at multiple | B83: =$G$54 | C83: =$G$54*($C$61+$C$70) | D83: =$G$54*($D$61+$D$70)
A84: TV at multiple | B84: =$H$54 | C84: =$H$54*($C$61+$C$70) | D84: =$H$54*($D$61+$D$70)
A86: 2.11 What the 2026-31 growth programme is worth at end-2031 (Base vs No growth) | B86: 2026 | C86: 2027 | D86: 2028 | E86: 2029 | F86: 2030 | G86: 2031 | H86: Total | L86: Source / explanation
A87: Year | B87: ='1 Earnings'!F342 | C87: ='1 Earnings'!G342 | D87: ='1 Earnings'!H342 | E87: ='1 Earnings'!I342 | F87: ='1 Earnings'!J342 | G87: ='1 Earnings'!K342
A88: Base distributable cash | B88: ='1 Earnings'!F430 | C88: ='1 Earnings'!G430 | D88: ='1 Earnings'!H430 | E88: ='1 Earnings'!I430 | F88: ='1 Earnings'!J430 | G88: ='1 Earnings'!K430 | H88: =SUM(B88:G88)
A89: No-growth distributable cash | B89: ='1 Earnings'!F618 | C89: ='1 Earnings'!G618 | D89: ='1 Earnings'!H618 | E89: ='1 Earnings'!I618 | F89: ='1 Earnings'!J618 | G89: ='1 Earnings'!K618 | H89: =SUM(B89:G89)
A90: Difference (Base less No growth) | B90: =B88-B89 | C90: =C88-C89 | D90: =D88-D89 | E90: =E88-E89 | F90: =F88-F89 | G90: =G88-G89 | H90: =SUM(B90:G90)
A91: Compounding factor to end-2031 at cross-check rate | B91: =(1+$B$18)^($G$87-B87) | C91: =(1+$B$18)^($G$87-C87) | D91: =(1+$B$18)^($G$87-D87) | E91: =(1+$B$18)^($G$87-E87) | F91: =(1+$B$18)^($G$87-F87) | G91: =(1+$B$18)^($G$87-G87)
A92: Difference compounded to end-2031 | H92: =SUMPRODUCT(B90:G90,B91:G91)
A93: Extra terminal value from 2026-31 locations | H93: =C73-D73
A94: Net value of the growth programme at end-2031 | H94: =H93+H92 | L94: Close to nil: growth capex ~value-neutral
A96: 2.12 Cross-check: value-driver formula on Owners' Earnings | B96: Bear | C96: Base | D96: No growth | E96: Bull | L96: Source / explanation
A97: Total steady-state growth g | B97: =B10+B11 | C97: =C10+C11 | D97: =D10+D11 | E97: =E10+E11
A98: Reinvestment rate = share growth / OE yield | B98: =B11/B12 | C98: =C11/C12 | D98: =D11/D12 | E98: =E11/E12
A99: Fundamental TV/OE at cross-check rate = (1+g)(1-reinv)/(r-g) | B99: =(1+B97)*(1-B98)/($B$18-B97) | C99: =(1+C97)*(1-C98)/($B$18-C97) | D99: =(1+D97)*(1-D98)/($B$18-D97) | E99: =(1+E97)*(1-E98)/($B$18-E97)
A100: Chosen TV / OE (from 2.9) | B100: =B74 | C100: =C74 | D100: =D74 | E100: =E74
A101: Discount rate implied by the chosen TV | B101: =B97+(1+B97)*(1-B98)/B100 | C101: =C97+(1+C97)*(1-C98)/C100 | D101: =D97+(1+D97)*(1-D98)/D100 | E101: =E97+(1+E97)*(1-E98)/E100 | L101: Chosen deal multiples imply ~8-9% returns
A103: 2.13 Base value-driver TV/OE grid (rows = discount rate, columns = total growth)
A104: Total growth g | B104: =B56 | C104: =C56 | D104: =D56 | E104: =E56
A105: TV/OE at discount rate 8% (row input 2.7 col B) | B105: =(1+$B$104)*(1-$C$11/$C$12)/($B$55-$B$104) | C105: =(1+$C$104)*(1-$C$11/$C$12)/($B$55-$C$104) | D105: =(1+$D$104)*(1-$C$11/$C$12)/($B$55-$D$104) | E105: =(1+$E$104)*(1-$C$11/$C$12)/($B$55-$E$104)
A106: TV/OE at discount rate 9% (row input 2.7 col C) | B106: =(1+$B$104)*(1-$C$11/$C$12)/($C$55-$B$104) | C106: =(1+$C$104)*(1-$C$11/$C$12)/($C$55-$C$104) | D106: =(1+$D$104)*(1-$C$11/$C$12)/($C$55-$D$104) | E106: =(1+$E$104)*(1-$C$11/$C$12)/($C$55-$E$104)
A107: TV/OE at discount rate 10% (row input 2.7 col D) | B107: =(1+$B$104)*(1-$C$11/$C$12)/($D$55-$B$104) | C107: =(1+$C$104)*(1-$C$11/$C$12)/($D$55-$C$104) | D107: =(1+$D$104)*(1-$C$11/$C$12)/($D$55-$D$104) | E107: =(1+$E$104)*(1-$C$11/$C$12)/($D$55-$E$104)
A109: 2.14 Other cross-checks | B109: Value | L109: Source / explanation
A110: Impairment-test cash-flow multiple at WACC high | B110: =(1+B15)/(B17-B15)
A111: Impairment-test cash-flow multiple at WACC low | B111: =(1+B15)/(B16-B15)
A112: Base: EBITDA lost if existing margin normalized to target | B112: =(C65-B19)*C66
A113: Base: TV lower by | B113: =C7*B112
A114: Joe Hudson's: net price (price less tax benefits) | B114: =B37-B38
...

Sheet 3 SOTP Valuation
A1: Boyd Group Services (BYD.TO) - Sheet 3: Sum-of-the-parts valuation per share
A2: US$ millions unless stated. Value = PV(2026-31 distributable cash) + PV(terminal value) + standalone assets - debt. Python source: valuation.py. Trading price not used.
A3: Input (change me) | B3: Linked from elsewhere (do not overwrite) | F3: Black = formula
A5: INPUTS
A6: 3.1 Valuation settings and case weights | B6: Value | L6: Source / explanation
A7: Discount rate | B7: 0.1 | L7: Task requirement (valuation.py ValuationSettings)
A8: Valuation year (t = 0, not discounted) | B8: 2026
A9: Terminal year (TV sits at end of this year) | B9: 2031
A10: Case weights | B10: Bear | C10: Base | D10: No growth | E10: Bull | L10: Source / explanation
A11: Weight in headline value | B11: 0.25 | C11: 0.25 | D11: 0.25 | E11: 0.25 | L11: No growth shares the base drivers, so takes half the base's 50% (valuation.md sec 1)
A13: 3.2 H1-2026 actuals (to strip realized cash out of FY2026E) | B13: Value | L13: Source / explanation
A14: H1-2026 Adjusted EBITDA | B14: ='1 Earnings'!F12 | L14: Linked to sheet 1
A15: H1-2026 cash rent | B15: ='1 Earnings'!F13+'1 Earnings'!F14+'1 Earnings'!F15+'1 Earnings'!F16 | L15: Linked to sheet 1
A16: H1-2026 net growth spend (acquisitions & development less sale-leasebacks, ex-JH) | B16: 32.9 | L16: forecast_earnings.md sec 6.1a, H1-2026 row
A18: 3.3 Balance sheet at Jun-30-2026 (Q2FY26 FS) | B18: Value | L18: Source / explanation
A19: Cash | B19: 22.969 | L19: Balance sheet
A20: Operating cash requirement | B20: 25 | L20: owners_earnings_and_roic.md sec 4: cash capped at $25M as operating
A21: Revolver + swing line (net of financing costs) | B21: 285.253 | L21: Note 11
A22: Term Loan A (net of financing costs) | B22: 124.963 | L22: Note 11
A23: Seller notes (deferred acquisition consideration) | B23: 8.606 | L23: Note 11
A24: Senior notes 2030, US$ (C$525M principal) | B24: 369.443 | L24: Note 12
A25: Senior notes 2033, US$ (C$275M principal) | B25: 193.517 | L25: Note 12
A26: Dividends payable | B26: 3.056 | L26: Balance sheet
A27: Cross-currency swaps - asset | B27: 4.305 | L27: Balance sheet
A28: Cross-currency swaps - liability | B28: 3.003 | L28: Balance sheet
A29: Memo: lease liabilities, current (NOT deducted) | B29: 159.574 | L29: Rent is charged in full inside Owners' Earnings; deducting would double count
A30: Memo: lease liabilities, non-current (NOT deducted) | B30: 891.311
A31: Memo: deferred tax liability (NOT deducted) | B31: 104.318
A32: Memo: deferred tax asset | B32: 10.051
A34: 3.4 Goodwill & intangible tax shields (value outside OE, which is taxed at full rate) | B34: Value | L34: Source / explanation
A35: Joe Hudson's tax benefits, Boyd's estimate | B35: ='2 Terminal Value'!B38 | L35: Linked to sheet 2 (JH release l.43)
A36: Joe Hudson's goodwill (book) | B36: 521.76 | L36: Q2FY26 FS acquisition table l.249-258
A37: Joe Hudson's customer relationships | B37: 700 | L37: Same table
A38: Joe Hudson's brand | B38: 0.5 | L38: Same table
A39: Joe Hudson's intellectual property | B39: 0.3 | L39: Same table
A40: Legacy goodwill, Dec-2025 | B40: 702.46 | L40: Q2FY26 FS l.28, Dec-25 column
A41: Legacy intangibles (net), Dec-2025 | B41: 356.347 | L41: Same
A42: Other 2026 acquisitions: goodwill | B42: 7.208 | L42: Q2FY26 FS acquisition table, 'Other acquisitions'
A43: Other 2026 acquisitions: customer relationships | B43: 5.496 | L43: Same
A44: Other 2026 acquisitions: non-competes | B44: 0.245 | L44: Same
A45: Cross-check: JH tax-deductible goodwill | B45: 366.291 | L45: Q2FY26 FS l.316
A46: Cross-check: JH tax-deductible intangibles | B46: 602.555 | L46: Q2FY26 FS l.318
A47: Cross-check: US tax amortization life (years) | B47: 15 | L47: From internal AI model knowledge: IRC s.197 15-year straight line
A48: Cross-check: share of 2026 deduction still to come | B48: 0.5 | L48: H1-2026 benefit already inside Jun-26 cash
A49: Tax rate | B49: ='1 Earnings'!B30 | L49: Linked to sheet 1
A51: 3.5 Share count and FX | B51: Value | L51: Source / explanation
A52: Basic shares outstanding, Jun-30-2026 | B52: 27836435 | L52: Q2FY26 FS statement of changes in equity
A53: Diluted weighted shares, Q2-2026 | B53: 27898269 | L53: Q2FY26 FS l.129
A54: Basic weighted shares, Q2-2026 | B54: 27836295 | L54: Q2FY26 FS l.128
A55: Share option plan cap | B55: 250000 | L55: FY2025 AFS l.459
A56: C$ principal of senior notes (525 + 275) | B56: 800 | L56: FY2025 MD&A l.25, l.35
A57: US$ carrying principal of senior notes | B57: =B24+B25 | L57: Linked to 3.3
A59: 3.6 Sensitivity axes
A60: Discount rates to test | B60: 0.08 | C60: 0.09 | D60: 0.1 | E60: 0.11 | F60: 0.12
A61: Exit multiple shifts to test (all cases) | B61: -1.5 | C61: -1 | D61: -0.5 | E61: 0 | F61: 0.5 | G61: 1
A63: CALCULATIONS
A64: 3.7 Timeline and discount factors | B64: 2026 | C64: 2027 | D64: 2028 | E64: 2029 | F64: 2030 | G64: 2031 | L64: Source / explanation
A65: Year | B65: =B8 | C65: =B65+1 | D65: =C65+1 | E65: =D65+1 | F65: =E65+1 | G65: =F65+1
A66: t (years from valuation year) | B66: =B65-$B$8 | C66: =C65-$B$8 | D66: =D65-$B$8 | E66: =E65-$B$8 | F66: =F65-$B$8 | G66: =G65-$B$8
A67: Discount factor | B67: =1/(1+$B$7)^B66 | C67: =1/(1+$B$7)^C66 | D67: =1/(1+$B$7)^D66 | E67: =1/(1+$B$7)^E66 | F67: =1/(1+$B$7)^F66 | G67: =1/(1+$B$7)^G66
A68: Discount factor at terminal year | B68: =1/(1+B7)^(B9-B8)
A70: 3.8 FY2026 stub: only H2-2026 cash counts (H1 is inside Jun-26 net debt) | B70: Bear | C70: Base | D70: No growth | E70: Bull | L70: Source / explanation
A71: FY2026E Owners' Earnings | B71: ='1 Earnings'!F329 | C71: ='1 Earnings'!F423 | D71: ='1 Earnings'!F611 | E71: ='1 Earnings'!F517 | L71: Linked to sheet 1
A72: FY2026E EBITDA after rent | B72: ='1 Earnings'!F324 | C72: ='1 Earnings'!F418 | D72: ='1 Earnings'!F606 | E72: ='1 Earnings'!F512
A73: FY2026E growth capex | B73: ='1 Earnings'!F316 | C73: ='1 Earnings'!F410 | D73: ='1 Earnings'!F598 | E73: ='1 Earnings'!F504
A74: FY2026E one-offs (all Jul-2026 onward) | B74: ='1 Earnings'!F335 | C74: ='1 Earnings'!F429 | D74: ='1 Earnings'!F617 | E74: ='1 Earnings'!F523
A75: H2 share of FY2026E OE (proxy: H2 share of EBITDA after rent) | B75: =(B72-($B$14-$B$15))/B72 | C75: =(C72-($B$14-$B$15))/C72 | D75: =(D72-($B$14-$B$15))/D72 | E75: =(E72-($B$14-$B$15))/E72
A76: H2-2026 Owners' Earnings | B76: =B71*B75 | C76: =C71*C75 | D76: =D71*D75 | E76: =E71*E75
A77: H2-2026 growth capex = FY less H1 actual (floor 0) | B77: =MAX(B73-$B$16,0) | C77: =MAX(C73-$B$16,0) | D77: =MAX(D73-$B$16,0) | E77: =MAX(E73-$B$16,0)
A78: H2-2026 distributable cash | B78: =B76-B77-B74 | C78: =C76-C77-C74 | D78: =D76-D77-D74 | E78: =E76-E77-E74
A80: 3.9 Distributable cash counted in the valuation | B80: 2026 | C80: 2027 | D80: 2028 | E80: 2029 | F80: 2030 | G80: 2031 | H80: PV | L80: Source / explanation
A81: Bear | B81: =B78 | C81: ='1 Earnings'!G336 | D81: ='1 Earnings'!H336 | E81: ='1 Earnings'!I336 | F81: ='1 Earnings'!J336 | G81: ='1 Earnings'!K336 | H81: =SUMPRODUCT(B81:G81,$B$67:$G$67) | L81: 2026 = H2 stub (3.8); 2027-31 linked to sheet 1
A82: Base | B82: =C78 | C82: ='1 Earnings'!G430 | D82: ='1 Earnings'!H430 | E82: ='1 Earnings'!I430 | F82: ='1 Earnings'!J430 | G82: ='1 Earnings'!K430 | H82: =SUMPRODUCT(B82:G82,$B$67:$G$67) | L82: 2026 = H2 stub (3.8); 2027-31 linked to sheet 1
A83: No growth (existing business only) | B83: =D78 | C83: ='1 Earnings'!G618 | D83: ='1 Earnings'!H618 | E83: ='1 Earnings'!I618 | F83: ='1 Earnings'!J618 | G83: ='1 Earnings'!K618 | H83: =SUMPRODUCT(B83:G83,$B$67:$G$67) | L83: 2026 = H2 stub (3.8); 2027-31 linked to sheet 1
A84: Bull | B84: =E78 | C84: ='1 Earnings'!G524 | D84: ='1 Earnings'!H524 | E84: ='1 Earnings'!I524 | F84: ='1 Earnings'!J524 | G84: ='1 Earnings'!K524 | H84: =SUMPRODUCT(B84:G84,$B$67:$G$67) | L84: 2026 = H2 stub (3.8); 2027-31 linked to sheet 1
A86: 3.10 Standalone assets and debt (computed once, same for every case) | B86: Value | L86: Source / explanation
A87: Excess cash above operating requirement | B87: =MAX(B19-B20,0)
A88: JH goodwill + intangibles (book) | B88: =B36+B37+B38+B39
A89: Legacy goodwill + intangibles (book) | B89: =B40+B41
A90: Other 2026 goodwill + intangibles | B90: =B42+B43+B44
A91: JH tax shield (Boyd's estimate) | B91: =B35
A92: Legacy tax shield = JH estimate x legacy / JH book ratio | B92: =B35*B89/B88 | L92: Inference: assumes pre-2023 goodwill is as deductible as 2023-25 goodwill (disclosed deductible)
A93: Other 2026 acquisitions tax shield (same ratio method) | B93: =B35*B90/B88
A94: Standalone assets, total | B94: =B87+B91+B92+B93
A95: Cross-currency swaps, net asset | B95: =B27-B28
A96: Debt and debt-like items, total | B96: =B21+B22+B23+B24+B25+B26-B95 | L96: Leases and deferred tax deliberately excluded (3.3 memo)
A97: Diluted shares (millions) = basic + dilutive RSU/PSU | B97: =(B52+B53-B54)/1000000 | L97: Options anti-dilutive (Q2FY26 FS l.669)
A98: C$ per US$ implied by Boyd's own note balances | B98: =B56/B57 | L98: No market FX used
A100: 3.11 SUM OF THE PARTS - intrinsic value per share (headline, exit-multiple TV) | B100: Bear | C100: Base | D100: No growth | E100: Bull | F100: Weighted | L100: Source / explanation
A101: PV of 2026-31 distributable cash | B101: =H81 | C101: =H82 | D101: =H83 | E101: =H84 | F101: =SUMPRODUCT($B$11:$E$11,B101:E101)
A102: Terminal value, end-2031 (sheet 2) | B102: ='2 Terminal Value'!B73 | C102: ='2 Terminal Value'!C73 | D102: ='2 Terminal Value'!D73 | E102: ='2 Terminal Value'!E73 | F102: =SUMPRODUCT($B$11:$E$11,B102:E102)
A103: PV of terminal value | B103: =B102*$B$68 | C103: =C102*$B$68 | D103: =D102*$B$68 | E103: =E102*$B$68 | F103: =SUMPRODUCT($B$11:$E$11,B103:E103)
A104: Enterprise value (operating business) | B104: =B101+B103 | C104: =C101+C103 | D104: =D101+D103 | E104: =E101+E103 | F104: =SUMPRODUCT($B$11:$E$11,B104:E104)
A105: terminal value share of EV | B105: =B103/B104 | C105: =C103/C104 | D105: =D103/D104 | E105: =E103/E104 | F105: =F103/F104
A106: Plus: excess cash | B106: =$B$87 | C106: =$B$87 | D106: =$B$87 | E106: =$B$87 | F106: =$B$87
A107: Plus: JH tax shield | B107: =$B$91 | C107: =$B$91 | D107: =$B$91 | E107: =$B$91 | F107: =$B$91
A108: Plus: legacy goodwill & intangibles tax shield | B108: =$B$92 | C108: =$B$92 | D108: =$B$92 | E108: =$B$92 | F108: =$B$92
A109: Plus: other 2026 tax shield | B109: =$B$93 | C109: =$B$93 | D109: =$B$93 | E109: =$B$93 | F109: =$B$93
A110: Less: revolver + swing line | B110: =-$B$21 | C110: =-$B$21 | D110: =-$B$21 | E110: =-$B$21 | F110: =-$B$21
A111: Less: Term Loan A | B111: =-$B$22 | C111: =-$B$22 | D111: =-$B$22 | E111: =-$B$22 | F111: =-$B$22
...
